{
  "generated_at": "2026-05-30T04:57:28.556069+00:00",
  "days_of_data": 10,
  "date_range": {
    "from": "2026-05-18",
    "to": "2026-05-30"
  },
  "languages": {
    "Tamil": {
      "days_tracked": 10,
      "dominant_genre": "Indie",
      "top_artists": [
        {
          "name": "IJAS",
          "appearances": 21,
          "avg_views": 6244,
          "avg_eng": 7.6,
          "top_genre": "Hip Hop / Rap"
        },
        {
          "name": "BeatZ of Lanka Remix",
          "appearances": 21,
          "avg_views": 1111,
          "avg_eng": 4.0,
          "top_genre": "Folk / Acoustic"
        },
        {
          "name": "Sanathan Shree Krishnan",
          "appearances": 19,
          "avg_views": 610920,
          "avg_eng": 4.1,
          "top_genre": "Indie"
        },
        {
          "name": "Sivakarthikeyan Productions",
          "appearances": 19,
          "avg_views": 146553,
          "avg_eng": 9.1,
          "top_genre": "Indie"
        },
        {
          "name": "Shweta Mohan",
          "appearances": 16,
          "avg_views": 68413,
          "avg_eng": 3.5,
          "top_genre": "Indie"
        }
      ],
      "genre_breakdown": [
        {
          "genre": "Indie",
          "day_appearances": 52
        },
        {
          "genre": "Folk / Acoustic",
          "day_appearances": 42
        },
        {
          "genre": "Hip Hop / Rap",
          "day_appearances": 37
        },
        {
          "genre": "R&B / Soul",
          "day_appearances": 26
        },
        {
          "genre": "Classical/Fusion",
          "day_appearances": 15
        },
        {
          "genre": "Lo-Fi",
          "day_appearances": 8
        },
        {
          "genre": "Electronic",
          "day_appearances": 6
        },
        {
          "genre": "Rock / Alt",
          "day_appearances": 3
        }
      ],
      "genre_insights": {
        "Indie": {
          "day_appearances": 52,
          "top_artists": [
            {
              "name": "Sivakarthikeyan Productions",
              "appearances": 13
            },
            {
              "name": "Sanathan Shree Krishnan",
              "appearances": 11
            },
            {
              "name": "Shweta Mohan",
              "appearances": 10
            }
          ]
        },
        "Folk / Acoustic": {
          "day_appearances": 42,
          "top_artists": [
            {
              "name": "BeatZ of Lanka Remix",
              "appearances": 18
            },
            {
              "name": "WHISTLE STUDIOS",
              "appearances": 13
            },
            {
              "name": "Relare Ganga",
              "appearances": 10
            }
          ]
        },
        "Hip Hop / Rap": {
          "day_appearances": 37,
          "top_artists": [
            {
              "name": "IJAS",
              "appearances": 21
            },
            {
              "name": "Shark Swami Music",
              "appearances": 12
            },
            {
              "name": "Chengalpattu Music Studio Johnson",
              "appearances": 1
            }
          ]
        },
        "R&B / Soul": {
          "day_appearances": 26,
          "top_artists": [
            {
              "name": "Big Indie Music(BIM)",
              "appearances": 9
            },
            {
              "name": "Shweta Mohan",
              "appearances": 6
            },
            {
              "name": "Sivakarthikeyan Productions",
              "appearances": 6
            }
          ]
        },
        "Classical/Fusion": {
          "day_appearances": 15,
          "top_artists": [
            {
              "name": "Sanathan Shree Krishnan",
              "appearances": 8
            },
            {
              "name": "DJ SRIRAM 96 ",
              "appearances": 5
            },
            {
              "name": "Kalaiyagam Original's",
              "appearances": 1
            }
          ]
        }
      },
      "view_trend": [
        {
          "date": "2026-05-20",
          "views": 114287,
          "videos": 12
        },
        {
          "date": "2026-05-21",
          "views": 18684,
          "videos": 2
        },
        {
          "date": "2026-05-22",
          "views": 8554417,
          "videos": 25
        },
        {
          "date": "2026-05-23",
          "views": 2995665,
          "videos": 25
        },
        {
          "date": "2026-05-24",
          "views": 3327369,
          "videos": 25
        },
        {
          "date": "2026-05-25",
          "views": 3706889,
          "videos": 25
        },
        {
          "date": "2026-05-26",
          "views": 4031205,
          "videos": 25
        },
        {
          "date": "2026-05-28",
          "views": 3616208,
          "videos": 25
        },
        {
          "date": "2026-05-30",
          "views": 3361627,
          "videos": 25
        }
      ],
      "narrative": "Recurring artists across 10 days: IJAS, BeatZ of Lanka Remix, Sanathan Shree Krishnan. Dominant genre: Indie (52 video-appearances across 10 day(s)). Also tracked: Folk / Acoustic (42), Hip Hop / Rap (37), R&B / Soul (26)."
    },
    "Telugu": {
      "days_tracked": 10,
      "dominant_genre": "Folk / Acoustic",
      "top_artists": [
        {
          "name": "Let's Mix Masala",
          "appearances": 19,
          "avg_views": 11762,
          "avg_eng": 2.6,
          "top_genre": "Lo-Fi"
        },
        {
          "name": "Telangana folk",
          "appearances": 19,
          "avg_views": 4282,
          "avg_eng": 3.2,
          "top_genre": "Hip Hop / Rap"
        },
        {
          "name": "Entertainment Express",
          "appearances": 15,
          "avg_views": 2695,
          "avg_eng": 3.8,
          "top_genre": "R&B / Soul"
        },
        {
          "name": "Musiclife",
          "appearances": 13,
          "avg_views": 99485,
          "avg_eng": 3.4,
          "top_genre": "Indie"
        },
        {
          "name": "C SHOR",
          "appearances": 11,
          "avg_views": 6574,
          "avg_eng": 5.5,
          "top_genre": "Indie"
        }
      ],
      "genre_breakdown": [
        {
          "genre": "Folk / Acoustic",
          "day_appearances": 44
        },
        {
          "genre": "Hip Hop / Rap",
          "day_appearances": 42
        },
        {
          "genre": "Indie",
          "day_appearances": 41
        },
        {
          "genre": "R&B / Soul",
          "day_appearances": 23
        },
        {
          "genre": "Lo-Fi",
          "day_appearances": 9
        },
        {
          "genre": "Classical/Fusion",
          "day_appearances": 9
        },
        {
          "genre": "Electronic",
          "day_appearances": 9
        }
      ],
      "genre_insights": {
        "Folk / Acoustic": {
          "day_appearances": 44,
          "top_artists": [
            {
              "name": "Amulya Studio",
              "appearances": 10
            },
            {
              "name": "DJ NARI CREATIONS",
              "appearances": 10
            },
            {
              "name": "mv_music_fan_club",
              "appearances": 9
            }
          ]
        },
        "Hip Hop / Rap": {
          "day_appearances": 42,
          "top_artists": [
            {
              "name": "Telangana folk",
              "appearances": 15
            },
            {
              "name": "C SHOR",
              "appearances": 5
            },
            {
              "name": "Bilip Songs",
              "appearances": 5
            }
          ]
        },
        "Indie": {
          "day_appearances": 41,
          "top_artists": [
            {
              "name": "Musiclife",
              "appearances": 11
            },
            {
              "name": "C SHOR",
              "appearances": 6
            },
            {
              "name": "Entertainment Express",
              "appearances": 5
            }
          ]
        },
        "R&B / Soul": {
          "day_appearances": 23,
          "top_artists": [
            {
              "name": "Madhura Audio Originals",
              "appearances": 6
            },
            {
              "name": "Entertainment Express",
              "appearances": 6
            },
            {
              "name": "MANN MUSIC ORIGINALS",
              "appearances": 5
            }
          ]
        },
        "Lo-Fi": {
          "day_appearances": 9,
          "top_artists": [
            {
              "name": "Let's Mix Masala",
              "appearances": 7
            },
            {
              "name": "MANN MUSIC ORIGINALS",
              "appearances": 1
            },
            {
              "name": "parasar_musings \ud83c\uddee\ud83c\uddf3 ",
              "appearances": 1
            }
          ]
        }
      },
      "view_trend": [
        {
          "date": "2026-05-21",
          "views": 11373,
          "videos": 2
        },
        {
          "date": "2026-05-22",
          "views": 4100560,
          "videos": 25
        },
        {
          "date": "2026-05-23",
          "views": 2281277,
          "videos": 25
        },
        {
          "date": "2026-05-24",
          "views": 2349382,
          "videos": 25
        },
        {
          "date": "2026-05-25",
          "views": 2477360,
          "videos": 25
        },
        {
          "date": "2026-05-26",
          "views": 322092,
          "videos": 25
        },
        {
          "date": "2026-05-28",
          "views": 2477489,
          "videos": 25
        },
        {
          "date": "2026-05-30",
          "views": 123899,
          "videos": 25
        }
      ],
      "narrative": "Recurring artists across 10 days: Let's Mix Masala, Telangana folk, Entertainment Express. Dominant genre: Folk / Acoustic (44 video-appearances across 10 day(s)). Also tracked: Hip Hop / Rap (42), Indie (41), R&B / Soul (23)."
    },
    "Kannada": {
      "days_tracked": 10,
      "dominant_genre": "Folk / Acoustic",
      "top_artists": [
        {
          "name": "MRSU MUSIC",
          "appearances": 19,
          "avg_views": 73250,
          "avg_eng": 5.0,
          "top_genre": "Hip Hop / Rap"
        },
        {
          "name": "Siri Beats",
          "appearances": 19,
          "avg_views": 4002,
          "avg_eng": 1.7,
          "top_genre": "Electronic"
        },
        {
          "name": "PRASAD SHOKDAR",
          "appearances": 18,
          "avg_views": 36336,
          "avg_eng": 9.7,
          "top_genre": "Hip Hop / Rap"
        },
        {
          "name": "Kousthuba Entertainments",
          "appearances": 16,
          "avg_views": 60824,
          "avg_eng": 1.5,
          "top_genre": "Indie"
        },
        {
          "name": "Uttara Karnataka Jawari Folk Songs",
          "appearances": 15,
          "avg_views": 14588,
          "avg_eng": 2.8,
          "top_genre": "Folk / Acoustic"
        }
      ],
      "genre_breakdown": [
        {
          "genre": "Folk / Acoustic",
          "day_appearances": 42
        },
        {
          "genre": "Hip Hop / Rap",
          "day_appearances": 42
        },
        {
          "genre": "Indie",
          "day_appearances": 39
        },
        {
          "genre": "R&B / Soul",
          "day_appearances": 26
        },
        {
          "genre": "Electronic",
          "day_appearances": 17
        },
        {
          "genre": "Lo-Fi",
          "day_appearances": 3
        },
        {
          "genre": "Indie Pop",
          "day_appearances": 2
        },
        {
          "genre": "Classical/Fusion",
          "day_appearances": 2
        },
        {
          "genre": "Rock / Alt",
          "day_appearances": 1
        }
      ],
      "genre_insights": {
        "Folk / Acoustic": {
          "day_appearances": 42,
          "top_artists": [
            {
              "name": "Uttara Karnataka Jawari Folk Songs",
              "appearances": 15
            },
            {
              "name": "Dj Malakari Alagawadi",
              "appearances": 5
            },
            {
              "name": "K Music Telugu Folk",
              "appearances": 5
            }
          ]
        },
        "Hip Hop / Rap": {
          "day_appearances": 42,
          "top_artists": [
            {
              "name": "MRSU MUSIC",
              "appearances": 19
            },
            {
              "name": "PRASAD SHOKDAR",
              "appearances": 18
            },
            {
              "name": "PKSG Musics",
              "appearances": 1
            }
          ]
        },
        "Indie": {
          "day_appearances": 39,
          "top_artists": [
            {
              "name": "Kousthuba Entertainments",
              "appearances": 15
            },
            {
              "name": "Nanna ki",
              "appearances": 11
            },
            {
              "name": "Manjunath Hosaval",
              "appearances": 6
            }
          ]
        },
        "R&B / Soul": {
          "day_appearances": 26,
          "top_artists": [
            {
              "name": "ChanduCreations ",
              "appearances": 13
            },
            {
              "name": "Sid's Music Garage",
              "appearances": 11
            },
            {
              "name": "\u0cb8\u0c82\u0ca6\u0cc7\u0cb6 \u0cb5\u0cbf\u0cb6\u0cc7\u0cb7 \ud835\udd4a\ud835\udd52\ud835\udd5f\ud835\udd55\ud835\udd56\ud835\udd64\ud835\udd59'\ud835\udd64 \ud835\udd4a\ud835\udd61\ud835\udd56\ud835\udd54\ud835\udd5a\ud835\udd52\ud835\udd5d",
              "appearances": 2
            }
          ]
        },
        "Electronic": {
          "day_appearances": 17,
          "top_artists": [
            {
              "name": "Siri Beats",
              "appearances": 14
            },
            {
              "name": "Veeru Jamakandi Singer - Topic",
              "appearances": 3
            }
          ]
        }
      },
      "view_trend": [
        {
          "date": "2026-05-20",
          "views": 5752,
          "videos": 3
        },
        {
          "date": "2026-05-22",
          "views": 8083129,
          "videos": 21
        },
        {
          "date": "2026-05-23",
          "views": 474722,
          "videos": 25
        },
        {
          "date": "2026-05-24",
          "views": 597655,
          "videos": 25
        },
        {
          "date": "2026-05-25",
          "views": 409638,
          "videos": 25
        },
        {
          "date": "2026-05-26",
          "views": 421448,
          "videos": 25
        },
        {
          "date": "2026-05-28",
          "views": 2778341,
          "videos": 25
        },
        {
          "date": "2026-05-30",
          "views": 3611414,
          "videos": 25
        }
      ],
      "narrative": "Recurring artists across 10 days: MRSU MUSIC, Siri Beats, PRASAD SHOKDAR. Dominant genre: Folk / Acoustic (42 video-appearances across 10 day(s)). Also tracked: Hip Hop / Rap (42), Indie (39), R&B / Soul (26)."
    },
    "Malayalam": {
      "days_tracked": 10,
      "dominant_genre": "Indie",
      "top_artists": [
        {
          "name": "Gallery Vision Indie",
          "appearances": 21,
          "avg_views": 105902,
          "avg_eng": 5.1,
          "top_genre": "Electronic"
        },
        {
          "name": "Patrick Michael",
          "appearances": 20,
          "avg_views": 35172,
          "avg_eng": 4.5,
          "top_genre": "Classical/Fusion"
        },
        {
          "name": "Baizyeah",
          "appearances": 20,
          "avg_views": 1057,
          "avg_eng": 7.3,
          "top_genre": "Hip Hop / Rap"
        },
        {
          "name": "VEDAN with word",
          "appearances": 19,
          "avg_views": 241623,
          "avg_eng": 5.2,
          "top_genre": "Electronic"
        },
        {
          "name": "Nadham Arts",
          "appearances": 19,
          "avg_views": 27453,
          "avg_eng": 7.0,
          "top_genre": "Indie"
        }
      ],
      "genre_breakdown": [
        {
          "genre": "Indie",
          "day_appearances": 53
        },
        {
          "genre": "Hip Hop / Rap",
          "day_appearances": 41
        },
        {
          "genre": "Folk / Acoustic",
          "day_appearances": 35
        },
        {
          "genre": "Electronic",
          "day_appearances": 34
        },
        {
          "genre": "Classical/Fusion",
          "day_appearances": 17
        },
        {
          "genre": "Lo-Fi",
          "day_appearances": 6
        },
        {
          "genre": "R&B / Soul",
          "day_appearances": 1
        }
      ],
      "genre_insights": {
        "Indie": {
          "day_appearances": 53,
          "top_artists": [
            {
              "name": "Shamil koppam",
              "appearances": 14
            },
            {
              "name": "Nadham Arts",
              "appearances": 12
            },
            {
              "name": "Baizyeah",
              "appearances": 4
            }
          ]
        },
        "Hip Hop / Rap": {
          "day_appearances": 41,
          "top_artists": [
            {
              "name": "Baizyeah",
              "appearances": 13
            },
            {
              "name": "Nabzy Nabuhan",
              "appearances": 9
            },
            {
              "name": "Gallery Vision Indie",
              "appearances": 6
            }
          ]
        },
        "Folk / Acoustic": {
          "day_appearances": 35,
          "top_artists": [
            {
              "name": "Nabzy Nabuhan",
              "appearances": 9
            },
            {
              "name": "Nadham Arts",
              "appearances": 7
            },
            {
              "name": "Razik Mujawar",
              "appearances": 7
            }
          ]
        },
        "Electronic": {
          "day_appearances": 34,
          "top_artists": [
            {
              "name": "Gallery Vision Indie",
              "appearances": 13
            },
            {
              "name": "VEDAN with word",
              "appearances": 12
            },
            {
              "name": "Mango Skyline",
              "appearances": 5
            }
          ]
        },
        "Classical/Fusion": {
          "day_appearances": 17,
          "top_artists": [
            {
              "name": "Patrick Michael",
              "appearances": 9
            },
            {
              "name": "Baizyeah",
              "appearances": 3
            },
            {
              "name": "JAGAN PRAYAT",
              "appearances": 2
            }
          ]
        }
      },
      "view_trend": [
        {
          "date": "2026-05-20",
          "views": 104677,
          "videos": 12
        },
        {
          "date": "2026-05-21",
          "views": 6242,
          "videos": 4
        },
        {
          "date": "2026-05-22",
          "views": 9481235,
          "videos": 21
        },
        {
          "date": "2026-05-23",
          "views": 875144,
          "videos": 25
        },
        {
          "date": "2026-05-24",
          "views": 1315023,
          "videos": 25
        },
        {
          "date": "2026-05-25",
          "views": 971402,
          "videos": 25
        },
        {
          "date": "2026-05-26",
          "views": 3353790,
          "videos": 25
        },
        {
          "date": "2026-05-28",
          "views": 1152411,
          "videos": 25
        },
        {
          "date": "2026-05-30",
          "views": 928790,
          "videos": 25
        }
      ],
      "narrative": "Recurring artists across 10 days: Gallery Vision Indie, Patrick Michael, Baizyeah. Dominant genre: Indie (53 video-appearances across 10 day(s)). Also tracked: Hip Hop / Rap (41), Folk / Acoustic (35), Electronic (34)."
    },
    "Bengali": {
      "days_tracked": 10,
      "dominant_genre": "Indie",
      "top_artists": [
        {
          "name": "Manchu Dada",
          "appearances": 19,
          "avg_views": 177165,
          "avg_eng": 7.0,
          "top_genre": "Hip Hop / Rap"
        },
        {
          "name": "Obydullah Tarek",
          "appearances": 19,
          "avg_views": 8347,
          "avg_eng": 6.4,
          "top_genre": "Indie"
        },
        {
          "name": "Kittu",
          "appearances": 18,
          "avg_views": 8746,
          "avg_eng": 8.5,
          "top_genre": "Indie"
        },
        {
          "name": "DADA BHAI INDIA",
          "appearances": 16,
          "avg_views": 162844,
          "avg_eng": 4.9,
          "top_genre": "Indie"
        },
        {
          "name": "Suman Babu Music ",
          "appearances": 15,
          "avg_views": 1657,
          "avg_eng": 1.5,
          "top_genre": "Lo-Fi"
        }
      ],
      "genre_breakdown": [
        {
          "genre": "Indie",
          "day_appearances": 44
        },
        {
          "genre": "Folk / Acoustic",
          "day_appearances": 44
        },
        {
          "genre": "Lo-Fi",
          "day_appearances": 38
        },
        {
          "genre": "Hip Hop / Rap",
          "day_appearances": 35
        },
        {
          "genre": "Rock / Alt",
          "day_appearances": 14
        },
        {
          "genre": "Electronic",
          "day_appearances": 5
        },
        {
          "genre": "Jazz / Blues",
          "day_appearances": 3
        }
      ],
      "genre_insights": {
        "Indie": {
          "day_appearances": 44,
          "top_artists": [
            {
              "name": "DADA BHAI INDIA",
              "appearances": 12
            },
            {
              "name": "JOCHONA BARI",
              "appearances": 8
            },
            {
              "name": "Obydullah Tarek",
              "appearances": 8
            }
          ]
        },
        "Folk / Acoustic": {
          "day_appearances": 44,
          "top_artists": [
            {
              "name": "Sohail Mia",
              "appearances": 12
            },
            {
              "name": "Rajib Shah ",
              "appearances": 6
            },
            {
              "name": "Tonmoy Baul Media",
              "appearances": 5
            }
          ]
        },
        "Lo-Fi": {
          "day_appearances": 38,
          "top_artists": [
            {
              "name": "Suman Babu Music ",
              "appearances": 15
            },
            {
              "name": "Palash Melody",
              "appearances": 11
            },
            {
              "name": "Suman Ruj",
              "appearances": 8
            }
          ]
        },
        "Hip Hop / Rap": {
          "day_appearances": 35,
          "top_artists": [
            {
              "name": "Manchu Dada",
              "appearances": 13
            },
            {
              "name": "Obydullah Tarek",
              "appearances": 7
            },
            {
              "name": "JOCHONA BARI",
              "appearances": 6
            }
          ]
        },
        "Rock / Alt": {
          "day_appearances": 14,
          "top_artists": [
            {
              "name": "Kittu",
              "appearances": 6
            },
            {
              "name": "Neel Shor",
              "appearances": 4
            },
            {
              "name": "Ghost Composer",
              "appearances": 2
            }
          ]
        }
      },
      "view_trend": [
        {
          "date": "2026-05-21",
          "views": 42366,
          "videos": 8
        },
        {
          "date": "2026-05-22",
          "views": 1812635,
          "videos": 25
        },
        {
          "date": "2026-05-23",
          "views": 827154,
          "videos": 25
        },
        {
          "date": "2026-05-24",
          "views": 838207,
          "videos": 25
        },
        {
          "date": "2026-05-25",
          "views": 1174884,
          "videos": 25
        },
        {
          "date": "2026-05-26",
          "views": 1193497,
          "videos": 25
        },
        {
          "date": "2026-05-28",
          "views": 1026618,
          "videos": 25
        },
        {
          "date": "2026-05-30",
          "views": 819194,
          "videos": 25
        }
      ],
      "narrative": "Recurring artists across 10 days: Manchu Dada, Obydullah Tarek, Kittu. Dominant genre: Indie (44 video-appearances across 10 day(s)). Also tracked: Folk / Acoustic (44), Lo-Fi (38), Hip Hop / Rap (35)."
    },
    "Punjabi": {
      "days_tracked": 10,
      "dominant_genre": "Indie",
      "top_artists": [
        {
          "name": "Sing With Suhani",
          "appearances": 19,
          "avg_views": 1495,
          "avg_eng": 5.3,
          "top_genre": "Folk / Acoustic"
        },
        {
          "name": "Sawinder Creations",
          "appearances": 18,
          "avg_views": 168107,
          "avg_eng": 2.1,
          "top_genre": "R&B / Soul"
        },
        {
          "name": "Hardik Bhardwaj Official",
          "appearances": 17,
          "avg_views": 59877,
          "avg_eng": 8.0,
          "top_genre": "Indie"
        },
        {
          "name": "Bakwas Rap",
          "appearances": 14,
          "avg_views": 863,
          "avg_eng": 4.4,
          "top_genre": "Hip Hop / Rap"
        },
        {
          "name": "Gurlluv Gill Music",
          "appearances": 13,
          "avg_views": 1049976,
          "avg_eng": 6.7,
          "top_genre": "Indie"
        }
      ],
      "genre_breakdown": [
        {
          "genre": "Indie",
          "day_appearances": 42
        },
        {
          "genre": "Folk / Acoustic",
          "day_appearances": 42
        },
        {
          "genre": "Hip Hop / Rap",
          "day_appearances": 38
        },
        {
          "genre": "Lo-Fi",
          "day_appearances": 26
        },
        {
          "genre": "R&B / Soul",
          "day_appearances": 21
        },
        {
          "genre": "Electronic",
          "day_appearances": 8
        }
      ],
      "genre_insights": {
        "Indie": {
          "day_appearances": 42,
          "top_artists": [
            {
              "name": "Hardik Bhardwaj Official",
              "appearances": 15
            },
            {
              "name": "Gurlluv Gill Music",
              "appearances": 13
            },
            {
              "name": "Indie Vibe Studios",
              "appearances": 3
            }
          ]
        },
        "Folk / Acoustic": {
          "day_appearances": 42,
          "top_artists": [
            {
              "name": "Sing With Suhani",
              "appearances": 19
            },
            {
              "name": "Desi Virsa Punjab",
              "appearances": 8
            },
            {
              "name": "Rang Music",
              "appearances": 6
            }
          ]
        },
        "Hip Hop / Rap": {
          "day_appearances": 38,
          "top_artists": [
            {
              "name": "Bakwas Rap",
              "appearances": 14
            },
            {
              "name": "Luck E",
              "appearances": 7
            },
            {
              "name": "SS The Rapstar",
              "appearances": 5
            }
          ]
        },
        "Lo-Fi": {
          "day_appearances": 26,
          "top_artists": [
            {
              "name": "Aarunvoxbeats",
              "appearances": 11
            },
            {
              "name": "Arman Study Studio",
              "appearances": 6
            },
            {
              "name": "Sufi Flow",
              "appearances": 6
            }
          ]
        },
        "R&B / Soul": {
          "day_appearances": 21,
          "top_artists": [
            {
              "name": "Sawinder Creations",
              "appearances": 18
            },
            {
              "name": "Hardik Bhardwaj Official",
              "appearances": 2
            },
            {
              "name": "Sakku Ki Ibadat official ",
              "appearances": 1
            }
          ]
        }
      },
      "view_trend": [
        {
          "date": "2026-05-21",
          "views": 442033,
          "videos": 2
        },
        {
          "date": "2026-05-22",
          "views": 10728442,
          "videos": 25
        },
        {
          "date": "2026-05-23",
          "views": 2326868,
          "videos": 25
        },
        {
          "date": "2026-05-24",
          "views": 5447190,
          "videos": 25
        },
        {
          "date": "2026-05-25",
          "views": 2191039,
          "videos": 25
        },
        {
          "date": "2026-05-26",
          "views": 3068605,
          "videos": 25
        },
        {
          "date": "2026-05-28",
          "views": 2550333,
          "videos": 25
        },
        {
          "date": "2026-05-30",
          "views": 2593879,
          "videos": 25
        }
      ],
      "narrative": "Recurring artists across 10 days: Sing With Suhani, Sawinder Creations, Hardik Bhardwaj Official. Dominant genre: Indie (42 video-appearances across 10 day(s)). Also tracked: Folk / Acoustic (42), Hip Hop / Rap (38), Lo-Fi (26)."
    },
    "Marathi": {
      "days_tracked": 10,
      "dominant_genre": "Indie",
      "top_artists": [
        {
          "name": "AGRI BABA",
          "appearances": 21,
          "avg_views": 5141,
          "avg_eng": 8.0,
          "top_genre": "Hip Hop / Rap"
        },
        {
          "name": "Morya Pratishthan Malewadi Borgaon",
          "appearances": 18,
          "avg_views": 1175,
          "avg_eng": 3.7,
          "top_genre": "Folk / Acoustic"
        },
        {
          "name": "SAMBATA__ 00",
          "appearances": 17,
          "avg_views": 744272,
          "avg_eng": 4.1,
          "top_genre": "Indie"
        },
        {
          "name": "OLD IS GOLD MUSIC",
          "appearances": 17,
          "avg_views": 1443,
          "avg_eng": 0.9,
          "top_genre": "R&B / Soul"
        },
        {
          "name": "Sur Dil Marathi  ",
          "appearances": 15,
          "avg_views": 8980,
          "avg_eng": 1.3,
          "top_genre": "Folk / Acoustic"
        }
      ],
      "genre_breakdown": [
        {
          "genre": "Indie",
          "day_appearances": 43
        },
        {
          "genre": "Hip Hop / Rap",
          "day_appearances": 42
        },
        {
          "genre": "Folk / Acoustic",
          "day_appearances": 39
        },
        {
          "genre": "Rock / Alt",
          "day_appearances": 15
        },
        {
          "genre": "R&B / Soul",
          "day_appearances": 13
        },
        {
          "genre": "Lo-Fi",
          "day_appearances": 11
        },
        {
          "genre": "Electronic",
          "day_appearances": 5
        },
        {
          "genre": "Classical/Fusion",
          "day_appearances": 3
        }
      ],
      "genre_insights": {
        "Indie": {
          "day_appearances": 43,
          "top_artists": [
            {
              "name": "SAMBATA__ 00",
              "appearances": 10
            },
            {
              "name": "Psh Gaonkar",
              "appearances": 10
            },
            {
              "name": "PRAKASH JADHAV ",
              "appearances": 9
            }
          ]
        },
        "Hip Hop / Rap": {
          "day_appearances": 42,
          "top_artists": [
            {
              "name": "AGRI BABA",
              "appearances": 21
            },
            {
              "name": "Patange Music ",
              "appearances": 9
            },
            {
              "name": "The Zero Plays",
              "appearances": 6
            }
          ]
        },
        "Folk / Acoustic": {
          "day_appearances": 39,
          "top_artists": [
            {
              "name": "Morya Pratishthan Malewadi Borgaon",
              "appearances": 18
            },
            {
              "name": "Sur Dil Marathi  ",
              "appearances": 8
            },
            {
              "name": "Dj KDM",
              "appearances": 4
            }
          ]
        },
        "Rock / Alt": {
          "day_appearances": 15,
          "top_artists": [
            {
              "name": "Dj KDM",
              "appearances": 8
            },
            {
              "name": "SAMBATA__ 00",
              "appearances": 6
            },
            {
              "name": "DJ Rushikesh Official",
              "appearances": 1
            }
          ]
        },
        "R&B / Soul": {
          "day_appearances": 13,
          "top_artists": [
            {
              "name": "OLD IS GOLD MUSIC",
              "appearances": 11
            },
            {
              "name": "Sur Dil Marathi  ",
              "appearances": 2
            }
          ]
        }
      },
      "view_trend": [
        {
          "date": "2026-05-21",
          "views": 1898,
          "videos": 1
        },
        {
          "date": "2026-05-22",
          "views": 9595968,
          "videos": 22
        },
        {
          "date": "2026-05-23",
          "views": 2722082,
          "videos": 25
        },
        {
          "date": "2026-05-24",
          "views": 2836565,
          "videos": 25
        },
        {
          "date": "2026-05-25",
          "views": 2768109,
          "videos": 25
        },
        {
          "date": "2026-05-26",
          "views": 2211862,
          "videos": 25
        },
        {
          "date": "2026-05-28",
          "views": 2421095,
          "videos": 24
        },
        {
          "date": "2026-05-30",
          "views": 2905774,
          "videos": 24
        }
      ],
      "narrative": "Recurring artists across 10 days: AGRI BABA, Morya Pratishthan Malewadi Borgaon, SAMBATA__ 00. Dominant genre: Indie (43 video-appearances across 10 day(s)). Also tracked: Hip Hop / Rap (42), Folk / Acoustic (39), Rock / Alt (15)."
    },
    "Hindi": {
      "days_tracked": 10,
      "dominant_genre": "Indie",
      "top_artists": [
        {
          "name": "Memiixyz",
          "appearances": 23,
          "avg_views": 133353,
          "avg_eng": 5.8,
          "top_genre": "Hip Hop / Rap"
        },
        {
          "name": "Esther Hnamte Official",
          "appearances": 18,
          "avg_views": 307146,
          "avg_eng": 6.7,
          "top_genre": "Indie"
        },
        {
          "name": "Jazz Passport",
          "appearances": 18,
          "avg_views": 39815,
          "avg_eng": 4.9,
          "top_genre": "Jazz / Blues"
        },
        {
          "name": "Keyjool",
          "appearances": 17,
          "avg_views": 1008,
          "avg_eng": 2.9,
          "top_genre": "R&B / Soul"
        },
        {
          "name": "Desi Unplugged",
          "appearances": 16,
          "avg_views": 15547,
          "avg_eng": 1.1,
          "top_genre": "Folk / Acoustic"
        }
      ],
      "genre_breakdown": [
        {
          "genre": "Indie",
          "day_appearances": 226
        },
        {
          "genre": "Hip Hop / Rap",
          "day_appearances": 44
        },
        {
          "genre": "Lo-Fi",
          "day_appearances": 26
        },
        {
          "genre": "Folk / Acoustic",
          "day_appearances": 26
        },
        {
          "genre": "Jazz / Blues",
          "day_appearances": 18
        },
        {
          "genre": "R&B / Soul",
          "day_appearances": 12
        },
        {
          "genre": "Classical/Fusion",
          "day_appearances": 11
        },
        {
          "genre": "Rock / Alt",
          "day_appearances": 2
        }
      ],
      "genre_insights": {
        "Indie": {
          "day_appearances": 226,
          "top_artists": [
            {
              "name": "KARMA",
              "appearances": 13
            },
            {
              "name": "Esther Hnamte Official",
              "appearances": 12
            },
            {
              "name": "Think Music India",
              "appearances": 10
            }
          ]
        },
        "Hip Hop / Rap": {
          "day_appearances": 44,
          "top_artists": [
            {
              "name": "Memiixyz",
              "appearances": 19
            },
            {
              "name": "PaulXIndra",
              "appearances": 8
            },
            {
              "name": "DHH",
              "appearances": 7
            }
          ]
        },
        "Lo-Fi": {
          "day_appearances": 26,
          "top_artists": [
            {
              "name": "Keyjool",
              "appearances": 5
            },
            {
              "name": "Lo-fi 4790",
              "appearances": 5
            },
            {
              "name": "Flipgod Music",
              "appearances": 5
            }
          ]
        },
        "Folk / Acoustic": {
          "day_appearances": 26,
          "top_artists": [
            {
              "name": "Desi Unplugged",
              "appearances": 16
            },
            {
              "name": "Sufi e Roohani music ",
              "appearances": 6
            },
            {
              "name": "Keyjool",
              "appearances": 4
            }
          ]
        },
        "Jazz / Blues": {
          "day_appearances": 18,
          "top_artists": [
            {
              "name": "Jazz Passport",
              "appearances": 17
            },
            {
              "name": "KozAz Music",
              "appearances": 1
            }
          ]
        }
      },
      "view_trend": [
        {
          "date": "2026-05-18",
          "views": 3496311925,
          "videos": 183
        },
        {
          "date": "2026-05-20",
          "views": 1345,
          "videos": 1
        },
        {
          "date": "2026-05-21",
          "views": 44547,
          "videos": 6
        },
        {
          "date": "2026-05-22",
          "views": 2808314,
          "videos": 25
        },
        {
          "date": "2026-05-23",
          "views": 1478032,
          "videos": 25
        },
        {
          "date": "2026-05-24",
          "views": 1487169,
          "videos": 25
        },
        {
          "date": "2026-05-25",
          "views": 1059277,
          "videos": 25
        },
        {
          "date": "2026-05-26",
          "views": 1757023,
          "videos": 25
        },
        {
          "date": "2026-05-28",
          "views": 1269108,
          "videos": 25
        },
        {
          "date": "2026-05-30",
          "views": 1338878,
          "videos": 25
        }
      ],
      "narrative": "Recurring artists across 10 days: Memiixyz, Esther Hnamte Official, Jazz Passport. Dominant genre: Indie (226 video-appearances across 10 day(s)). Also tracked: Hip Hop / Rap (44), Lo-Fi (26), Folk / Acoustic (26)."
    },
    "English": {
      "days_tracked": 10,
      "dominant_genre": "Indie",
      "top_artists": [
        {
          "name": "Spotify India",
          "appearances": 19,
          "avg_views": 119983,
          "avg_eng": 8.8,
          "top_genre": "Indie"
        },
        {
          "name": "NaadVerse Musics",
          "appearances": 19,
          "avg_views": 38244,
          "avg_eng": 5.0,
          "top_genre": "Classical/Fusion"
        },
        {
          "name": "Fleep",
          "appearances": 19,
          "avg_views": 20903,
          "avg_eng": 4.5,
          "top_genre": "Folk / Acoustic"
        },
        {
          "name": "Inayat Kaur Bajaj",
          "appearances": 19,
          "avg_views": 2576,
          "avg_eng": 4.6,
          "top_genre": "Classical/Fusion"
        },
        {
          "name": "Simran Choudhary",
          "appearances": 17,
          "avg_views": 28393,
          "avg_eng": 4.2,
          "top_genre": "Hip Hop / Rap"
        }
      ],
      "genre_breakdown": [
        {
          "genre": "Indie",
          "day_appearances": 41
        },
        {
          "genre": "Hip Hop / Rap",
          "day_appearances": 36
        },
        {
          "genre": "Classical/Fusion",
          "day_appearances": 26
        },
        {
          "genre": "Folk / Acoustic",
          "day_appearances": 25
        },
        {
          "genre": "Jazz / Blues",
          "day_appearances": 14
        },
        {
          "genre": "R&B / Soul",
          "day_appearances": 10
        },
        {
          "genre": "Lo-Fi",
          "day_appearances": 9
        },
        {
          "genre": "Rock / Alt",
          "day_appearances": 8
        },
        {
          "genre": "Electronic",
          "day_appearances": 8
        }
      ],
      "genre_insights": {
        "Indie": {
          "day_appearances": 41,
          "top_artists": [
            {
              "name": "Spotify India",
              "appearances": 14
            },
            {
              "name": "DJ Roshan HKD Official",
              "appearances": 9
            },
            {
              "name": "Inayat Kaur Bajaj",
              "appearances": 5
            }
          ]
        },
        "Hip Hop / Rap": {
          "day_appearances": 36,
          "top_artists": [
            {
              "name": "Simran Choudhary",
              "appearances": 10
            },
            {
              "name": "AJ Music Beats",
              "appearances": 8
            },
            {
              "name": "Harshal Music",
              "appearances": 8
            }
          ]
        },
        "Classical/Fusion": {
          "day_appearances": 26,
          "top_artists": [
            {
              "name": "NaadVerse Musics",
              "appearances": 13
            },
            {
              "name": "Inayat Kaur Bajaj",
              "appearances": 7
            },
            {
              "name": "Fleep",
              "appearances": 6
            }
          ]
        },
        "Folk / Acoustic": {
          "day_appearances": 25,
          "top_artists": [
            {
              "name": "Simran Choudhary",
              "appearances": 7
            },
            {
              "name": "Fleep",
              "appearances": 7
            },
            {
              "name": "Yasser Desai Fun Club",
              "appearances": 3
            }
          ]
        },
        "Jazz / Blues": {
          "day_appearances": 14,
          "top_artists": [
            {
              "name": "Rashid Ali Official",
              "appearances": 8
            },
            {
              "name": "NaadVerse Musics",
              "appearances": 6
            }
          ]
        }
      },
      "view_trend": [
        {
          "date": "2026-05-21",
          "views": 7762,
          "videos": 2
        },
        {
          "date": "2026-05-22",
          "views": 13555647,
          "videos": 25
        },
        {
          "date": "2026-05-23",
          "views": 344273,
          "videos": 25
        },
        {
          "date": "2026-05-24",
          "views": 341494,
          "videos": 25
        },
        {
          "date": "2026-05-25",
          "views": 219549,
          "videos": 25
        },
        {
          "date": "2026-05-26",
          "views": 351373,
          "videos": 25
        },
        {
          "date": "2026-05-28",
          "views": 784922,
          "videos": 25
        },
        {
          "date": "2026-05-30",
          "views": 901440,
          "videos": 25
        }
      ],
      "narrative": "Recurring artists across 10 days: Spotify India, NaadVerse Musics, Fleep. Dominant genre: Indie (41 video-appearances across 10 day(s)). Also tracked: Hip Hop / Rap (36), Classical/Fusion (26), Folk / Acoustic (25)."
    }
  }
}