{
  "generated_at": "2026-05-23T10:24:35.531314+00:00",
  "days_of_data": 5,
  "date_range": {
    "from": "2026-05-18",
    "to": "2026-05-23"
  },
  "languages": {
    "Tamil": {
      "days_tracked": 5,
      "dominant_genre": "Indie",
      "top_artists": [
        {
          "name": "IJAS",
          "appearances": 6,
          "avg_views": 7946,
          "avg_eng": 6.8,
          "top_genre": "Hip Hop / Rap"
        },
        {
          "name": "BeatZ of Lanka Remix",
          "appearances": 6,
          "avg_views": 1533,
          "avg_eng": 3.6,
          "top_genre": "Folk / Acoustic"
        },
        {
          "name": "Sanathan Shree Krishnan",
          "appearances": 4,
          "avg_views": 911456,
          "avg_eng": 4.1,
          "top_genre": "Indie"
        },
        {
          "name": "Sivakarthikeyan Productions",
          "appearances": 4,
          "avg_views": 593805,
          "avg_eng": 8.3,
          "top_genre": "Indie"
        },
        {
          "name": "Shweta Mohan",
          "appearances": 4,
          "avg_views": 35643,
          "avg_eng": 4.2,
          "top_genre": "Indie"
        }
      ],
      "genre_breakdown": [
        {
          "genre": "Indie",
          "day_appearances": 22
        },
        {
          "genre": "Hip Hop / Rap",
          "day_appearances": 14
        },
        {
          "genre": "Folk / Acoustic",
          "day_appearances": 12
        },
        {
          "genre": "Lo-Fi",
          "day_appearances": 6
        },
        {
          "genre": "Classical/Fusion",
          "day_appearances": 4
        },
        {
          "genre": "R&B / Soul",
          "day_appearances": 4
        },
        {
          "genre": "Electronic",
          "day_appearances": 1
        },
        {
          "genre": "Rock / Alt",
          "day_appearances": 1
        }
      ],
      "genre_insights": {
        "Indie": {
          "day_appearances": 22,
          "top_artists": [
            {
              "name": "Shweta Mohan",
              "appearances": 3
            },
            {
              "name": "Sivakarthikeyan Productions",
              "appearances": 3
            },
            {
              "name": "Sanathan Shree Krishnan",
              "appearances": 3
            }
          ]
        },
        "Hip Hop / Rap": {
          "day_appearances": 14,
          "top_artists": [
            {
              "name": "IJAS",
              "appearances": 6
            },
            {
              "name": "Shark Swami Music",
              "appearances": 4
            },
            {
              "name": "Chengalpattu Music Studio Johnson",
              "appearances": 1
            }
          ]
        },
        "Folk / Acoustic": {
          "day_appearances": 12,
          "top_artists": [
            {
              "name": "BeatZ of Lanka Remix",
              "appearances": 6
            },
            {
              "name": "WHISTLE STUDIOS",
              "appearances": 3
            },
            {
              "name": "Relare Ganga",
              "appearances": 2
            }
          ]
        },
        "Lo-Fi": {
          "day_appearances": 6,
          "top_artists": [
            {
              "name": "Imir Music",
              "appearances": 3
            },
            {
              "name": "The Lyrical Guide ",
              "appearances": 3
            }
          ]
        },
        "Classical/Fusion": {
          "day_appearances": 4,
          "top_artists": [
            {
              "name": "DJ SRIRAM 96 ",
              "appearances": 2
            },
            {
              "name": "Sanathan Shree Krishnan",
              "appearances": 1
            },
            {
              "name": "Kalaiyagam Original's",
              "appearances": 1
            }
          ]
        }
      },
      "view_trend": [
        {
          "date": "2026-05-20",
          "views": 114287,
          "videos": 12
        },
        {
          "date": "2026-05-21",
          "views": 18684,
          "videos": 2
        },
        {
          "date": "2026-05-22",
          "views": 8554417,
          "videos": 25
        },
        {
          "date": "2026-05-23",
          "views": 2995665,
          "videos": 25
        }
      ],
      "narrative": "Recurring artists across 5 days: IJAS, BeatZ of Lanka Remix, Sanathan Shree Krishnan. Dominant genre: Indie (22 video-appearances across 5 day(s)). Also tracked: Hip Hop / Rap (14), Folk / Acoustic (12), Lo-Fi (6)."
    },
    "Telugu": {
      "days_tracked": 5,
      "dominant_genre": "Folk / Acoustic",
      "top_artists": [
        {
          "name": "DJ NARI CREATIONS",
          "appearances": 5,
          "avg_views": 30460,
          "avg_eng": 1.8,
          "top_genre": "Folk / Acoustic"
        },
        {
          "name": "Musiclife",
          "appearances": 4,
          "avg_views": 284063,
          "avg_eng": 3.3,
          "top_genre": "Indie"
        },
        {
          "name": "Let's Mix Masala",
          "appearances": 4,
          "avg_views": 35023,
          "avg_eng": 2.9,
          "top_genre": "Lo-Fi"
        },
        {
          "name": "Telangana folk",
          "appearances": 4,
          "avg_views": 924,
          "avg_eng": 1.8,
          "top_genre": "Hip Hop / Rap"
        },
        {
          "name": "mv_music_fan_club",
          "appearances": 3,
          "avg_views": 17409,
          "avg_eng": 2.1,
          "top_genre": "Folk / Acoustic"
        }
      ],
      "genre_breakdown": [
        {
          "genre": "Folk / Acoustic",
          "day_appearances": 14
        },
        {
          "genre": "Hip Hop / Rap",
          "day_appearances": 12
        },
        {
          "genre": "Indie",
          "day_appearances": 11
        },
        {
          "genre": "R&B / Soul",
          "day_appearances": 8
        },
        {
          "genre": "Lo-Fi",
          "day_appearances": 3
        },
        {
          "genre": "Classical/Fusion",
          "day_appearances": 2
        },
        {
          "genre": "Electronic",
          "day_appearances": 2
        }
      ],
      "genre_insights": {
        "Folk / Acoustic": {
          "day_appearances": 14,
          "top_artists": [
            {
              "name": "DJ NARI CREATIONS",
              "appearances": 5
            },
            {
              "name": "Amulya Studio",
              "appearances": 3
            },
            {
              "name": "mv_music_fan_club",
              "appearances": 3
            }
          ]
        },
        "Hip Hop / Rap": {
          "day_appearances": 12,
          "top_artists": [
            {
              "name": "Telangana folk",
              "appearances": 4
            },
            {
              "name": "C SHOR",
              "appearances": 2
            },
            {
              "name": "Bilip Songs",
              "appearances": 2
            }
          ]
        },
        "Indie": {
          "day_appearances": 11,
          "top_artists": [
            {
              "name": "Improve with mune",
              "appearances": 2
            },
            {
              "name": "Hindi Lyrics",
              "appearances": 2
            },
            {
              "name": "Musiclife",
              "appearances": 2
            }
          ]
        },
        "R&B / Soul": {
          "day_appearances": 8,
          "top_artists": [
            {
              "name": "Musiclife",
              "appearances": 2
            },
            {
              "name": "Madhura Audio Originals",
              "appearances": 2
            },
            {
              "name": "Entertainment Express",
              "appearances": 2
            }
          ]
        },
        "Lo-Fi": {
          "day_appearances": 3,
          "top_artists": [
            {
              "name": "Let's Mix Masala",
              "appearances": 2
            },
            {
              "name": "MANN MUSIC ORIGINALS",
              "appearances": 1
            }
          ]
        }
      },
      "view_trend": [
        {
          "date": "2026-05-21",
          "views": 11373,
          "videos": 2
        },
        {
          "date": "2026-05-22",
          "views": 4100560,
          "videos": 25
        },
        {
          "date": "2026-05-23",
          "views": 2281277,
          "videos": 25
        }
      ],
      "narrative": "Recurring artists across 5 days: DJ NARI CREATIONS, Musiclife, Let's Mix Masala. Dominant genre: Folk / Acoustic (14 video-appearances across 5 day(s)). Also tracked: Hip Hop / Rap (12), Indie (11), R&B / Soul (8)."
    },
    "Kannada": {
      "days_tracked": 5,
      "dominant_genre": "Folk / Acoustic",
      "top_artists": [
        {
          "name": "Kousthuba Entertainments",
          "appearances": 4,
          "avg_views": 205942,
          "avg_eng": 1.3,
          "top_genre": "Indie"
        },
        {
          "name": "MRSU MUSIC",
          "appearances": 4,
          "avg_views": 62484,
          "avg_eng": 5.1,
          "top_genre": "Hip Hop / Rap"
        },
        {
          "name": "PRASAD SHOKDAR",
          "appearances": 4,
          "avg_views": 61840,
          "avg_eng": 9.3,
          "top_genre": "Hip Hop / Rap"
        },
        {
          "name": "Uttara Karnataka Jawari Folk Songs",
          "appearances": 4,
          "avg_views": 22584,
          "avg_eng": 2.6,
          "top_genre": "Folk / Acoustic"
        },
        {
          "name": "Nanna ki",
          "appearances": 4,
          "avg_views": 12529,
          "avg_eng": 1.4,
          "top_genre": "Indie"
        }
      ],
      "genre_breakdown": [
        {
          "genre": "Folk / Acoustic",
          "day_appearances": 12
        },
        {
          "genre": "Hip Hop / Rap",
          "day_appearances": 12
        },
        {
          "genre": "Indie",
          "day_appearances": 9
        },
        {
          "genre": "R&B / Soul",
          "day_appearances": 8
        },
        {
          "genre": "Indie Pop",
          "day_appearances": 2
        },
        {
          "genre": "Lo-Fi",
          "day_appearances": 2
        },
        {
          "genre": "Electronic",
          "day_appearances": 2
        },
        {
          "genre": "Rock / Alt",
          "day_appearances": 1
        },
        {
          "genre": "Classical/Fusion",
          "day_appearances": 1
        }
      ],
      "genre_insights": {
        "Folk / Acoustic": {
          "day_appearances": 12,
          "top_artists": [
            {
              "name": "Uttara Karnataka Jawari Folk Songs",
              "appearances": 4
            },
            {
              "name": "Dj Malakari Alagawadi",
              "appearances": 2
            },
            {
              "name": "K Music Telugu Folk",
              "appearances": 2
            }
          ]
        },
        "Hip Hop / Rap": {
          "day_appearances": 12,
          "top_artists": [
            {
              "name": "MRSU MUSIC",
              "appearances": 4
            },
            {
              "name": "PRASAD SHOKDAR",
              "appearances": 4
            },
            {
              "name": "Kousthuba Entertainments",
              "appearances": 1
            }
          ]
        },
        "Indie": {
          "day_appearances": 9,
          "top_artists": [
            {
              "name": "Kousthuba Entertainments",
              "appearances": 3
            },
            {
              "name": "Nanna ki",
              "appearances": 2
            },
            {
              "name": "Panda  Bitz",
              "appearances": 1
            }
          ]
        },
        "R&B / Soul": {
          "day_appearances": 8,
          "top_artists": [
            {
              "name": "Chandu ai Music",
              "appearances": 3
            },
            {
              "name": "Sid's Music Garage",
              "appearances": 3
            },
            {
              "name": "\u0cb8\u0c82\u0ca6\u0cc7\u0cb6 \u0cb5\u0cbf\u0cb6\u0cc7\u0cb7 \ud835\udd4a\ud835\udd52\ud835\udd5f\ud835\udd55\ud835\udd56\ud835\udd64\ud835\udd59'\ud835\udd64 \ud835\udd4a\ud835\udd61\ud835\udd56\ud835\udd54\ud835\udd5a\ud835\udd52\ud835\udd5d",
              "appearances": 2
            }
          ]
        },
        "Indie Pop": {
          "day_appearances": 2,
          "top_artists": [
            {
              "name": "Yashaswi",
              "appearances": 2
            }
          ]
        }
      },
      "view_trend": [
        {
          "date": "2026-05-20",
          "views": 5752,
          "videos": 3
        },
        {
          "date": "2026-05-22",
          "views": 8083129,
          "videos": 21
        },
        {
          "date": "2026-05-23",
          "views": 474722,
          "videos": 25
        }
      ],
      "narrative": "Recurring artists across 5 days: Kousthuba Entertainments, MRSU MUSIC, PRASAD SHOKDAR. Dominant genre: Folk / Acoustic (12 video-appearances across 5 day(s)). Also tracked: Hip Hop / Rap (12), Indie (9), R&B / Soul (8)."
    },
    "Malayalam": {
      "days_tracked": 5,
      "dominant_genre": "Indie",
      "top_artists": [
        {
          "name": "Gallery Vision Indie",
          "appearances": 6,
          "avg_views": 148531,
          "avg_eng": 4.6,
          "top_genre": "Electronic"
        },
        {
          "name": "Baizyeah",
          "appearances": 6,
          "avg_views": 1445,
          "avg_eng": 5.5,
          "top_genre": "Hip Hop / Rap"
        },
        {
          "name": "Shamil koppam",
          "appearances": 5,
          "avg_views": 768217,
          "avg_eng": 3.6,
          "top_genre": "Indie"
        },
        {
          "name": "Patrick Michael",
          "appearances": 5,
          "avg_views": 124558,
          "avg_eng": 2.5,
          "top_genre": "Folk / Acoustic"
        },
        {
          "name": "Nabzy Nabuhan",
          "appearances": 5,
          "avg_views": 1607,
          "avg_eng": 2.6,
          "top_genre": "Hip Hop / Rap"
        }
      ],
      "genre_breakdown": [
        {
          "genre": "Indie",
          "day_appearances": 23
        },
        {
          "genre": "Hip Hop / Rap",
          "day_appearances": 13
        },
        {
          "genre": "Folk / Acoustic",
          "day_appearances": 9
        },
        {
          "genre": "Electronic",
          "day_appearances": 8
        },
        {
          "genre": "Classical/Fusion",
          "day_appearances": 7
        },
        {
          "genre": "R&B / Soul",
          "day_appearances": 1
        },
        {
          "genre": "Lo-Fi",
          "day_appearances": 1
        }
      ],
      "genre_insights": {
        "Indie": {
          "day_appearances": 23,
          "top_artists": [
            {
              "name": "Shamil koppam",
              "appearances": 4
            },
            {
              "name": "Rajesh Elappara",
              "appearances": 3
            },
            {
              "name": "Nadham Arts",
              "appearances": 2
            }
          ]
        },
        "Hip Hop / Rap": {
          "day_appearances": 13,
          "top_artists": [
            {
              "name": "Baizyeah",
              "appearances": 4
            },
            {
              "name": "Nabzy Nabuhan",
              "appearances": 4
            },
            {
              "name": "Gallery Vision Indie",
              "appearances": 2
            }
          ]
        },
        "Folk / Acoustic": {
          "day_appearances": 9,
          "top_artists": [
            {
              "name": "Patrick Michael",
              "appearances": 2
            },
            {
              "name": "Nadham Arts",
              "appearances": 2
            },
            {
              "name": "Razik Mujawar",
              "appearances": 2
            }
          ]
        },
        "Electronic": {
          "day_appearances": 8,
          "top_artists": [
            {
              "name": "Gallery Vision Indie",
              "appearances": 3
            },
            {
              "name": "VEDAN with word",
              "appearances": 3
            },
            {
              "name": "Shamil koppam",
              "appearances": 1
            }
          ]
        },
        "Classical/Fusion": {
          "day_appearances": 7,
          "top_artists": [
            {
              "name": "Patrick Michael",
              "appearances": 2
            },
            {
              "name": "Baizyeah",
              "appearances": 2
            },
            {
              "name": "JAGAN PRAYAT",
              "appearances": 1
            }
          ]
        }
      },
      "view_trend": [
        {
          "date": "2026-05-20",
          "views": 104677,
          "videos": 12
        },
        {
          "date": "2026-05-21",
          "views": 6242,
          "videos": 4
        },
        {
          "date": "2026-05-22",
          "views": 9481235,
          "videos": 21
        },
        {
          "date": "2026-05-23",
          "views": 875144,
          "videos": 25
        }
      ],
      "narrative": "Recurring artists across 5 days: Gallery Vision Indie, Baizyeah, Shamil koppam. Dominant genre: Indie (23 video-appearances across 5 day(s)). Also tracked: Hip Hop / Rap (13), Folk / Acoustic (9), Electronic (8)."
    },
    "Bengali": {
      "days_tracked": 5,
      "dominant_genre": "Indie",
      "top_artists": [
        {
          "name": "JOCHONA BARI",
          "appearances": 5,
          "avg_views": 7770,
          "avg_eng": 3.1,
          "top_genre": "Indie"
        },
        {
          "name": "Manchu Dada",
          "appearances": 4,
          "avg_views": 180510,
          "avg_eng": 7.9,
          "top_genre": "Hip Hop / Rap"
        },
        {
          "name": "DADA BHAI INDIA",
          "appearances": 4,
          "avg_views": 173325,
          "avg_eng": 4.7,
          "top_genre": "Indie"
        },
        {
          "name": "Obydullah Tarek",
          "appearances": 4,
          "avg_views": 15703,
          "avg_eng": 4.4,
          "top_genre": "Hip Hop / Rap"
        },
        {
          "name": "Kittu",
          "appearances": 4,
          "avg_views": 7748,
          "avg_eng": 8.5,
          "top_genre": "Indie"
        }
      ],
      "genre_breakdown": [
        {
          "genre": "Indie",
          "day_appearances": 14
        },
        {
          "genre": "Folk / Acoustic",
          "day_appearances": 14
        },
        {
          "genre": "Lo-Fi",
          "day_appearances": 11
        },
        {
          "genre": "Hip Hop / Rap",
          "day_appearances": 10
        },
        {
          "genre": "Rock / Alt",
          "day_appearances": 5
        },
        {
          "genre": "Jazz / Blues",
          "day_appearances": 3
        },
        {
          "genre": "Electronic",
          "day_appearances": 1
        }
      ],
      "genre_insights": {
        "Indie": {
          "day_appearances": 14,
          "top_artists": [
            {
              "name": "JOCHONA BARI",
              "appearances": 4
            },
            {
              "name": "DADA BHAI INDIA",
              "appearances": 3
            },
            {
              "name": "Kittu",
              "appearances": 2
            }
          ]
        },
        "Folk / Acoustic": {
          "day_appearances": 14,
          "top_artists": [
            {
              "name": "Sohail Mia",
              "appearances": 3
            },
            {
              "name": "Tonmoy Baul Media",
              "appearances": 3
            },
            {
              "name": "FA Music BD",
              "appearances": 2
            }
          ]
        },
        "Lo-Fi": {
          "day_appearances": 11,
          "top_artists": [
            {
              "name": "Suman Babu Music ",
              "appearances": 4
            },
            {
              "name": "Suman Ruj",
              "appearances": 3
            },
            {
              "name": "Neel Shor",
              "appearances": 1
            }
          ]
        },
        "Hip Hop / Rap": {
          "day_appearances": 10,
          "top_artists": [
            {
              "name": "Manchu Dada",
              "appearances": 3
            },
            {
              "name": "Obydullah Tarek",
              "appearances": 2
            },
            {
              "name": "JOCHONA BARI",
              "appearances": 1
            }
          ]
        },
        "Rock / Alt": {
          "day_appearances": 5,
          "top_artists": [
            {
              "name": "Neel Shor",
              "appearances": 2
            },
            {
              "name": "Ghost Composer",
              "appearances": 1
            },
            {
              "name": "Kittu",
              "appearances": 1
            }
          ]
        }
      },
      "view_trend": [
        {
          "date": "2026-05-21",
          "views": 42366,
          "videos": 8
        },
        {
          "date": "2026-05-22",
          "views": 1812635,
          "videos": 25
        },
        {
          "date": "2026-05-23",
          "views": 827154,
          "videos": 25
        }
      ],
      "narrative": "Recurring artists across 5 days: JOCHONA BARI, Manchu Dada, DADA BHAI INDIA. Dominant genre: Indie (14 video-appearances across 5 day(s)). Also tracked: Folk / Acoustic (14), Lo-Fi (11), Hip Hop / Rap (10)."
    },
    "Punjabi": {
      "days_tracked": 5,
      "dominant_genre": "Indie",
      "top_artists": [
        {
          "name": "Sawinder Creations",
          "appearances": 5,
          "avg_views": 265812,
          "avg_eng": 2.4,
          "top_genre": "R&B / Soul"
        },
        {
          "name": "Sing With Suhani",
          "appearances": 4,
          "avg_views": 1566,
          "avg_eng": 4.8,
          "top_genre": "Folk / Acoustic"
        },
        {
          "name": "Bakwas Rap",
          "appearances": 4,
          "avg_views": 1173,
          "avg_eng": 4.1,
          "top_genre": "Hip Hop / Rap"
        },
        {
          "name": "Aarunvoxbeats",
          "appearances": 4,
          "avg_views": 727,
          "avg_eng": 0.6,
          "top_genre": "Lo-Fi"
        },
        {
          "name": "Gurlluv Gill Music",
          "appearances": 3,
          "avg_views": 1260301,
          "avg_eng": 6.0,
          "top_genre": "Indie"
        }
      ],
      "genre_breakdown": [
        {
          "genre": "Indie",
          "day_appearances": 12
        },
        {
          "genre": "Folk / Acoustic",
          "day_appearances": 12
        },
        {
          "genre": "Hip Hop / Rap",
          "day_appearances": 10
        },
        {
          "genre": "Lo-Fi",
          "day_appearances": 9
        },
        {
          "genre": "R&B / Soul",
          "day_appearances": 7
        },
        {
          "genre": "Electronic",
          "day_appearances": 2
        }
      ],
      "genre_insights": {
        "Indie": {
          "day_appearances": 12,
          "top_artists": [
            {
              "name": "Gurlluv Gill Music",
              "appearances": 3
            },
            {
              "name": "Indie Vibe Studios",
              "appearances": 2
            },
            {
              "name": "Jordan Sandhu",
              "appearances": 2
            }
          ]
        },
        "Folk / Acoustic": {
          "day_appearances": 12,
          "top_artists": [
            {
              "name": "Sing With Suhani",
              "appearances": 4
            },
            {
              "name": "Safeer E Dard \u0633\u0641\u06cc\u0631\u0650 \u062f\u0631\u062f",
              "appearances": 3
            },
            {
              "name": "Desi Virsa Punjab",
              "appearances": 2
            }
          ]
        },
        "Hip Hop / Rap": {
          "day_appearances": 10,
          "top_artists": [
            {
              "name": "Bakwas Rap",
              "appearances": 4
            },
            {
              "name": "Luck E",
              "appearances": 2
            },
            {
              "name": "AUS BEATZz",
              "appearances": 2
            }
          ]
        },
        "Lo-Fi": {
          "day_appearances": 9,
          "top_artists": [
            {
              "name": "Aarunvoxbeats",
              "appearances": 4
            },
            {
              "name": "Arman Study Studio",
              "appearances": 3
            },
            {
              "name": "Soulmate Vibes Music",
              "appearances": 1
            }
          ]
        },
        "R&B / Soul": {
          "day_appearances": 7,
          "top_artists": [
            {
              "name": "Sawinder Creations",
              "appearances": 5
            },
            {
              "name": "Hardik Bhardwaj Official",
              "appearances": 2
            }
          ]
        }
      },
      "view_trend": [
        {
          "date": "2026-05-21",
          "views": 442033,
          "videos": 2
        },
        {
          "date": "2026-05-22",
          "views": 10728442,
          "videos": 25
        },
        {
          "date": "2026-05-23",
          "views": 2326868,
          "videos": 25
        }
      ],
      "narrative": "Recurring artists across 5 days: Sawinder Creations, Sing With Suhani, Bakwas Rap. Dominant genre: Indie (12 video-appearances across 5 day(s)). Also tracked: Folk / Acoustic (12), Hip Hop / Rap (10), Lo-Fi (9)."
    },
    "Marathi": {
      "days_tracked": 5,
      "dominant_genre": "Indie",
      "top_artists": [
        {
          "name": "SAMBATA__ 00",
          "appearances": 6,
          "avg_views": 1209354,
          "avg_eng": 3.6,
          "top_genre": "Indie"
        },
        {
          "name": "AGRI BABA",
          "appearances": 6,
          "avg_views": 6236,
          "avg_eng": 6.5,
          "top_genre": "Hip Hop / Rap"
        },
        {
          "name": "Dj KDM",
          "appearances": 4,
          "avg_views": 214422,
          "avg_eng": 0.4,
          "top_genre": "Folk / Acoustic"
        },
        {
          "name": "DJ Vaibhav In The Mix",
          "appearances": 4,
          "avg_views": 45386,
          "avg_eng": 1.0,
          "top_genre": "Hip Hop / Rap"
        },
        {
          "name": "Sur Dil Marathi  ",
          "appearances": 4,
          "avg_views": 8604,
          "avg_eng": 1.4,
          "top_genre": "Classical/Fusion"
        }
      ],
      "genre_breakdown": [
        {
          "genre": "Indie",
          "day_appearances": 13
        },
        {
          "genre": "Hip Hop / Rap",
          "day_appearances": 12
        },
        {
          "genre": "Folk / Acoustic",
          "day_appearances": 12
        },
        {
          "genre": "Rock / Alt",
          "day_appearances": 4
        },
        {
          "genre": "Lo-Fi",
          "day_appearances": 2
        },
        {
          "genre": "Electronic",
          "day_appearances": 2
        },
        {
          "genre": "R&B / Soul",
          "day_appearances": 2
        },
        {
          "genre": "Classical/Fusion",
          "day_appearances": 1
        }
      ],
      "genre_insights": {
        "Indie": {
          "day_appearances": 13,
          "top_artists": [
            {
              "name": "SAMBATA__ 00",
              "appearances": 4
            },
            {
              "name": "DJ Ravi RJ Official",
              "appearances": 3
            },
            {
              "name": "PRAKASH JADHAV ",
              "appearances": 2
            }
          ]
        },
        "Hip Hop / Rap": {
          "day_appearances": 12,
          "top_artists": [
            {
              "name": "AGRI BABA",
              "appearances": 6
            },
            {
              "name": "Patange Music ",
              "appearances": 2
            },
            {
              "name": "DJ Vaibhav In The Mix",
              "appearances": 2
            }
          ]
        },
        "Folk / Acoustic": {
          "day_appearances": 12,
          "top_artists": [
            {
              "name": "Morya Pratishthan Malewadi Borgaon",
              "appearances": 4
            },
            {
              "name": "OLD IS GOLD MUSIC",
              "appearances": 2
            },
            {
              "name": "Dj KDM",
              "appearances": 2
            }
          ]
        },
        "Rock / Alt": {
          "day_appearances": 4,
          "top_artists": [
            {
              "name": "Dj KDM",
              "appearances": 2
            },
            {
              "name": "SAMBATA__ 00",
              "appearances": 1
            },
            {
              "name": "DJ Rushikesh Official",
              "appearances": 1
            }
          ]
        },
        "Lo-Fi": {
          "day_appearances": 2,
          "top_artists": [
            {
              "name": "The Pratik Pakhale",
              "appearances": 2
            }
          ]
        }
      },
      "view_trend": [
        {
          "date": "2026-05-21",
          "views": 1898,
          "videos": 1
        },
        {
          "date": "2026-05-22",
          "views": 9595968,
          "videos": 22
        },
        {
          "date": "2026-05-23",
          "views": 2722082,
          "videos": 25
        }
      ],
      "narrative": "Recurring artists across 5 days: SAMBATA__ 00, AGRI BABA, Dj KDM. Dominant genre: Indie (13 video-appearances across 5 day(s)). Also tracked: Hip Hop / Rap (12), Folk / Acoustic (12), Rock / Alt (4)."
    },
    "Hindi": {
      "days_tracked": 5,
      "dominant_genre": "Indie",
      "top_artists": [
        {
          "name": "T-Series",
          "appearances": 10,
          "avg_views": 37883102,
          "avg_eng": 1.0,
          "top_genre": "Indie"
        },
        {
          "name": "Think Music India",
          "appearances": 10,
          "avg_views": 26701566,
          "avg_eng": 1.0,
          "top_genre": "Indie"
        },
        {
          "name": "Memiixyz",
          "appearances": 8,
          "avg_views": 379596,
          "avg_eng": 3.8,
          "top_genre": "Indie"
        },
        {
          "name": "Jazz Passport",
          "appearances": 5,
          "avg_views": 40731,
          "avg_eng": 4.7,
          "top_genre": "Jazz / Blues"
        },
        {
          "name": "Saregama Music",
          "appearances": 4,
          "avg_views": 38169356,
          "avg_eng": 0.6,
          "top_genre": "Indie"
        }
      ],
      "genre_breakdown": [
        {
          "genre": "Indie",
          "day_appearances": 196
        },
        {
          "genre": "Hip Hop / Rap",
          "day_appearances": 14
        },
        {
          "genre": "Lo-Fi",
          "day_appearances": 11
        },
        {
          "genre": "Folk / Acoustic",
          "day_appearances": 7
        },
        {
          "genre": "Jazz / Blues",
          "day_appearances": 5
        },
        {
          "genre": "R&B / Soul",
          "day_appearances": 3
        },
        {
          "genre": "Classical/Fusion",
          "day_appearances": 2
        },
        {
          "genre": "Rock / Alt",
          "day_appearances": 2
        }
      ],
      "genre_insights": {
        "Indie": {
          "day_appearances": 196,
          "top_artists": [
            {
              "name": "Think Music India",
              "appearances": 10
            },
            {
              "name": "T-Series",
              "appearances": 10
            },
            {
              "name": "Saregama Music",
              "appearances": 4
            }
          ]
        },
        "Hip Hop / Rap": {
          "day_appearances": 14,
          "top_artists": [
            {
              "name": "Memiixyz",
              "appearances": 4
            },
            {
              "name": "\u092a\u094b\u0938\u0935\u093e\u0932 \u092e\u094d\u092f\u0942\u091c\u093c\u093f\u0915 \u0916\u091f\u0915\u0921",
              "appearances": 3
            },
            {
              "name": "PaulXIndra",
              "appearances": 2
            }
          ]
        },
        "Lo-Fi": {
          "day_appearances": 11,
          "top_artists": [
            {
              "name": "VirDurgesh Music ",
              "appearances": 2
            },
            {
              "name": "Keyjool",
              "appearances": 2
            },
            {
              "name": "Lo-fi 4790",
              "appearances": 2
            }
          ]
        },
        "Folk / Acoustic": {
          "day_appearances": 7,
          "top_artists": [
            {
              "name": "Desi Unplugged",
              "appearances": 4
            },
            {
              "name": "Sufi e Roohani music ",
              "appearances": 2
            },
            {
              "name": "Keyjool",
              "appearances": 1
            }
          ]
        },
        "Jazz / Blues": {
          "day_appearances": 5,
          "top_artists": [
            {
              "name": "Jazz Passport",
              "appearances": 4
            },
            {
              "name": "KozAz Music",
              "appearances": 1
            }
          ]
        }
      },
      "view_trend": [
        {
          "date": "2026-05-18",
          "views": 3496311925,
          "videos": 183
        },
        {
          "date": "2026-05-20",
          "views": 1345,
          "videos": 1
        },
        {
          "date": "2026-05-21",
          "views": 44547,
          "videos": 6
        },
        {
          "date": "2026-05-22",
          "views": 2808314,
          "videos": 25
        },
        {
          "date": "2026-05-23",
          "views": 1478032,
          "videos": 25
        }
      ],
      "narrative": "Recurring artists across 5 days: T-Series, Think Music India, Memiixyz. Dominant genre: Indie (196 video-appearances across 5 day(s)). Also tracked: Hip Hop / Rap (14), Lo-Fi (11), Folk / Acoustic (7)."
    },
    "English": {
      "days_tracked": 5,
      "dominant_genre": "Indie",
      "top_artists": [
        {
          "name": "Inayat Kaur Bajaj",
          "appearances": 5,
          "avg_views": 3304,
          "avg_eng": 4.9,
          "top_genre": "Classical/Fusion"
        },
        {
          "name": "Spotify India",
          "appearances": 4,
          "avg_views": 516374,
          "avg_eng": 7.4,
          "top_genre": "Indie"
        },
        {
          "name": "NaadVerse Musics",
          "appearances": 4,
          "avg_views": 176170,
          "avg_eng": 4.3,
          "top_genre": "Jazz / Blues"
        },
        {
          "name": "Fleep",
          "appearances": 4,
          "avg_views": 20180,
          "avg_eng": 4.4,
          "top_genre": "Folk / Acoustic"
        },
        {
          "name": "DJ Dalal London",
          "appearances": 4,
          "avg_views": 17764,
          "avg_eng": 2.9,
          "top_genre": "Electronic"
        }
      ],
      "genre_breakdown": [
        {
          "genre": "Indie",
          "day_appearances": 12
        },
        {
          "genre": "Folk / Acoustic",
          "day_appearances": 10
        },
        {
          "genre": "Hip Hop / Rap",
          "day_appearances": 9
        },
        {
          "genre": "Classical/Fusion",
          "day_appearances": 6
        },
        {
          "genre": "Electronic",
          "day_appearances": 5
        },
        {
          "genre": "Rock / Alt",
          "day_appearances": 3
        },
        {
          "genre": "Jazz / Blues",
          "day_appearances": 3
        },
        {
          "genre": "Lo-Fi",
          "day_appearances": 2
        },
        {
          "genre": "R&B / Soul",
          "day_appearances": 2
        }
      ],
      "genre_insights": {
        "Indie": {
          "day_appearances": 12,
          "top_artists": [
            {
              "name": "DJ Roshan HKD Official",
              "appearances": 4
            },
            {
              "name": "AJ Music Beats",
              "appearances": 2
            },
            {
              "name": "Spotify India",
              "appearances": 2
            }
          ]
        },
        "Folk / Acoustic": {
          "day_appearances": 10,
          "top_artists": [
            {
              "name": "Simran Choudhary",
              "appearances": 2
            },
            {
              "name": "Fleep",
              "appearances": 2
            },
            {
              "name": "Inayat Kaur Bajaj",
              "appearances": 1
            }
          ]
        },
        "Hip Hop / Rap": {
          "day_appearances": 9,
          "top_artists": [
            {
              "name": "Harshal Music",
              "appearances": 2
            },
            {
              "name": "Simran Choudhary",
              "appearances": 1
            },
            {
              "name": "AJ Music Beats",
              "appearances": 1
            }
          ]
        },
        "Classical/Fusion": {
          "day_appearances": 6,
          "top_artists": [
            {
              "name": "Inayat Kaur Bajaj",
              "appearances": 3
            },
            {
              "name": "NaadVerse Musics",
              "appearances": 2
            },
            {
              "name": "Fleep",
              "appearances": 1
            }
          ]
        },
        "Electronic": {
          "day_appearances": 5,
          "top_artists": [
            {
              "name": "C3RB3RUS India",
              "appearances": 3
            },
            {
              "name": "DJ Dalal London",
              "appearances": 2
            }
          ]
        }
      },
      "view_trend": [
        {
          "date": "2026-05-21",
          "views": 7762,
          "videos": 2
        },
        {
          "date": "2026-05-22",
          "views": 13555647,
          "videos": 25
        },
        {
          "date": "2026-05-23",
          "views": 344273,
          "videos": 25
        }
      ],
      "narrative": "Recurring artists across 5 days: Inayat Kaur Bajaj, Spotify India, NaadVerse Musics. Dominant genre: Indie (12 video-appearances across 5 day(s)). Also tracked: Folk / Acoustic (10), Hip Hop / Rap (9), Classical/Fusion (6)."
    }
  }
}