{
  "2026-06": {
    "month": "2026-06",
    "snapshots": 13,
    "last_snapshot_at": "2026-06-15T06:31:28.056777+00:00",
    "total_videos": 225,
    "total_artists": 229,
    "new_artists_seen": 219,
    "median_score": 61,
    "median_views": 3929,
    "top_artists": [
      {
        "name": "Sivakarthikeyan Productions",
        "score": 99.3,
        "views": 4917,
        "genre": "Indie",
        "language": "Tamil"
      },
      {
        "name": "Swan Studios",
        "score": 99.3,
        "views": 803,
        "genre": "R&B / Soul",
        "language": "Tamil"
      },
      {
        "name": "Ramo Folk Originals",
        "score": 99.3,
        "views": 3202,
        "genre": "Hip Hop / Rap",
        "language": "Telugu"
      },
      {
        "name": "Nadham Arts",
        "score": 99.3,
        "views": 2317,
        "genre": "Folk / Acoustic",
        "language": "Malayalam"
      },
      {
        "name": "Desi Virsa Punjab",
        "score": 99.3,
        "views": 885,
        "genre": "Folk / Acoustic",
        "language": "Punjabi"
      },
      {
        "name": "Vibe chapters",
        "score": 99.3,
        "views": 2338,
        "genre": "Indie",
        "language": "Punjabi"
      },
      {
        "name": "MiMarathi-p7j",
        "score": 99.3,
        "views": 1698,
        "genre": "Indie",
        "language": "Marathi"
      },
      {
        "name": "Psh Gaonkar",
        "score": 99.3,
        "views": 882,
        "genre": "Indie",
        "language": "Marathi"
      },
      {
        "name": "DHH",
        "score": 99.3,
        "views": 635,
        "genre": "Hip Hop / Rap",
        "language": "Hindi"
      },
      {
        "name": "Memiixyz",
        "score": 99.3,
        "views": 595,
        "genre": "Hip Hop / Rap",
        "language": "Hindi"
      }
    ],
    "fastest_growing": [
      {
        "name": "Veeru Jamakandi Singer - Topic",
        "views_gained": 1587662,
        "genre": "Electronic",
        "language": "Kannada"
      },
      {
        "name": "Shreyashhh",
        "views_gained": 515147,
        "genre": "Indie",
        "language": "English"
      },
      {
        "name": "Lo-fi 2307",
        "views_gained": 338485,
        "genre": "Lo-Fi",
        "language": "English"
      },
      {
        "name": "Gallery Vision Indie",
        "views_gained": 270841,
        "genre": "Electronic",
        "language": "Malayalam"
      },
      {
        "name": "MRSU MUSIC",
        "views_gained": 173988,
        "genre": "Indie",
        "language": "Kannada"
      }
    ],
    "genre_breakdown": [
      [
        "Indie",
        54
      ],
      [
        "Hip Hop / Rap",
        47
      ],
      [
        "Folk / Acoustic",
        43
      ],
      [
        "Lo-Fi",
        22
      ],
      [
        "Classical/Fusion",
        17
      ],
      [
        "R&B / Soul",
        17
      ],
      [
        "Electronic",
        16
      ],
      [
        "Rock / Alt",
        4
      ],
      [
        "Jazz / Blues",
        3
      ],
      [
        "Indie Pop",
        2
      ]
    ],
    "language_breakdown": [
      [
        "Tamil",
        25
      ],
      [
        "Telugu",
        25
      ],
      [
        "Kannada",
        25
      ],
      [
        "Bengali",
        25
      ],
      [
        "Punjabi",
        25
      ],
      [
        "Marathi",
        25
      ],
      [
        "Hindi",
        25
      ],
      [
        "Malayalam",
        25
      ],
      [
        "English",
        25
      ]
    ],
    "city_shows": {
      "Goa": 24,
      "Bangalore": 58,
      "Guwahati": 2,
      "Mumbai": 20,
      "Kolkata": 8,
      "Chennai": 6,
      "Delhi": 12,
      "Hyderabad": 8,
      "Pune": 6,
      "Dwarka": 1,
      "Meerut": 1,
      "Tamil Nadu": 1,
      "Ladakh": 1,
      "Abu Dhabi": 1,
      "India": 1,
      "Manali": 1,
      "Patna": 1,
      "Dehradun": 1,
      "Kochi": 1,
      "Dharamshala": 1,
      "Udaipur": 1
    },
    "top_city": "Bangalore",
    "total_shows": 156
  }
}