{
  "generated_at": "2026-06-30T05:12:03.867419+00:00",
  "snapshot_date": "2026-06-30",
  "cities": {
    "Bangalore": {
      "total_shows": 87,
      "venues": [
        {
          "name": "BudBee Restobar 104",
          "shows": 4,
          "price_min": 49,
          "price_max": 49,
          "next_date": "2026-07-03",
          "growth": null
        },
        {
          "name": "Privilege",
          "shows": 3,
          "price_min": 799,
          "price_max": 4999,
          "next_date": "2026-07-05",
          "growth": 0
        },
        {
          "name": "Prestige Centre for Performing Arts",
          "shows": 2,
          "price_min": 1000,
          "price_max": 1000,
          "next_date": "2026-07-25",
          "growth": 0
        },
        {
          "name": "Chowdiah Memorial Hall",
          "shows": 2,
          "price_min": 300,
          "price_max": 499,
          "next_date": "2026-07-26",
          "growth": -1
        },
        {
          "name": "The Humming Tree",
          "shows": 2,
          "price_min": 299,
          "price_max": 799,
          "next_date": "2026-07-19",
          "growth": -1
        },
        {
          "name": "District Arena @ Terraform",
          "shows": 2,
          "price_min": 1999,
          "price_max": 5000,
          "next_date": "2026-09-19",
          "growth": 0
        },
        {
          "name": "YEDA REPUBLIC KORAMANGALA",
          "shows": 2,
          "price_min": null,
          "price_max": null,
          "next_date": "29 Jun Mon",
          "growth": null
        },
        {
          "name": "Sugar Factory Reloaded",
          "shows": 1,
          "price_min": null,
          "price_max": null,
          "next_date": "2026-06-30",
          "growth": null
        },
        {
          "name": "Silaa The Garden Cafe, Malleshwaram",
          "shows": 1,
          "price_min": 299,
          "price_max": 299,
          "next_date": "2026-07-01",
          "growth": -1
        },
        {
          "name": "FLO Church Street",
          "shows": 1,
          "price_min": 100,
          "price_max": 100,
          "next_date": "2026-07-01",
          "growth": null
        },
        {
          "name": "Vapour Pub And Brewery,  Indiranagar",
          "shows": 1,
          "price_min": null,
          "price_max": null,
          "next_date": "2026-07-02",
          "growth": null
        },
        {
          "name": "Gsuper Club and GToxe",
          "shows": 1,
          "price_min": 100,
          "price_max": 100,
          "next_date": "2026-07-02",
          "growth": 0
        },
        {
          "name": "Brau Galie Micro Brewery and Pub",
          "shows": 1,
          "price_min": 100,
          "price_max": 100,
          "next_date": "2026-07-03",
          "growth": null
        },
        {
          "name": "DND - The Venue",
          "shows": 1,
          "price_min": 499,
          "price_max": 499,
          "next_date": "2026-07-04",
          "growth": 0
        },
        {
          "name": "Mirror Pub",
          "shows": 1,
          "price_min": 100,
          "price_max": 100,
          "next_date": "2026-07-04",
          "growth": null
        },
        {
          "name": "Bloom Creative Zone, Akshaya Nagar",
          "shows": 1,
          "price_min": 349,
          "price_max": 349,
          "next_date": "2026-07-04",
          "growth": null
        },
        {
          "name": "Gilly`s 104",
          "shows": 1,
          "price_min": 49,
          "price_max": 49,
          "next_date": "2026-07-04",
          "growth": null
        },
        {
          "name": "Blah Bla",
          "shows": 1,
          "price_min": 49,
          "price_max": 49,
          "next_date": "2026-07-04",
          "growth": null
        },
        {
          "name": "Drava",
          "shows": 1,
          "price_min": null,
          "price_max": null,
          "next_date": "2026-07-05",
          "growth": 0
        },
        {
          "name": "Wadia Hall",
          "shows": 1,
          "price_min": 250,
          "price_max": 250,
          "next_date": "2026-07-05",
          "growth": null
        },
        {
          "name": "Namma Ashram",
          "shows": 1,
          "price_min": 399,
          "price_max": 399,
          "next_date": "2026-07-10",
          "growth": null
        },
        {
          "name": "ITI Ground",
          "shows": 1,
          "price_min": 999,
          "price_max": 999,
          "next_date": "2026-07-11",
          "growth": 0
        },
        {
          "name": "Telugu Vignana Samithi",
          "shows": 1,
          "price_min": 350,
          "price_max": 350,
          "next_date": "2026-07-11",
          "growth": null
        },
        {
          "name": "Yeda Republic",
          "shows": 1,
          "price_min": 499,
          "price_max": 499,
          "next_date": "2026-07-19",
          "growth": null
        },
        {
          "name": "FoxFire Dance Studio",
          "shows": 1,
          "price_min": 799,
          "price_max": 799,
          "next_date": "2026-07-25",
          "growth": null
        },
        {
          "name": "Forum South",
          "shows": 1,
          "price_min": 599,
          "price_max": 599,
          "next_date": "2026-08-22",
          "growth": null
        },
        {
          "name": "Venue To Be Announced",
          "shows": 1,
          "price_min": 999,
          "price_max": 999,
          "next_date": "2026-08-22",
          "growth": 0
        },
        {
          "name": "NICE Grounds",
          "shows": 1,
          "price_min": 4000,
          "price_max": 4000,
          "next_date": "2026-11-14",
          "growth": 0
        },
        {
          "name": "Phoenix Market City",
          "shows": 1,
          "price_min": 799,
          "price_max": 799,
          "next_date": "2026-11-28",
          "growth": null
        },
        {
          "name": "Multiple Cities",
          "shows": 1,
          "price_min": null,
          "price_max": null,
          "next_date": "2026-12-05",
          "growth": null
        },
        {
          "name": "JP Nagara Social | JP Nagar,",
          "shows": 1,
          "price_min": 299,
          "price_max": 299,
          "next_date": "2026-07-04",
          "growth": 0
        },
        {
          "name": "BudBee 104 Resto Bar | Koramangala 7th Block,",
          "shows": 1,
          "price_min": 199,
          "price_max": 199,
          "next_date": "2026-07-04",
          "growth": -1
        },
        {
          "name": "Sarjapur SOCIAL | Sarjapur Road,",
          "shows": 1,
          "price_min": 449,
          "price_max": 449,
          "next_date": "2026-07-11",
          "growth": 0
        },
        {
          "name": "OTP-Oven Tawa Pan",
          "shows": 1,
          "price_min": 299,
          "price_max": 299,
          "next_date": "2026-07-11",
          "growth": null
        },
        {
          "name": "Phoenix Mall Of Asia",
          "shows": 1,
          "price_min": 999,
          "price_max": 999,
          "next_date": "2026-08-08",
          "growth": null
        },
        {
          "name": "Venue to be announced",
          "shows": 1,
          "price_min": 999,
          "price_max": 999,
          "next_date": "2026-11-14",
          "growth": 0
        },
        {
          "name": "THT Ground Floor Bar 2",
          "shows": 1,
          "price_min": null,
          "price_max": null,
          "next_date": "2026-07-02",
          "growth": 0
        },
        {
          "name": "THT Ground Floor Bar 9",
          "shows": 1,
          "price_min": null,
          "price_max": null,
          "next_date": "2026-07-09",
          "growth": 0
        },
        {
          "name": "Space Is All We Have (Album Launch) x Yogieatsprog ft. Fallen Letters & Munz TDT",
          "shows": 1,
          "price_min": 499,
          "price_max": 499,
          "next_date": "2026-07-11",
          "growth": 0
        },
        {
          "name": "THT Ground Floor Bar 16",
          "shows": 1,
          "price_min": null,
          "price_max": null,
          "next_date": "2026-07-16",
          "growth": 0
        },
        {
          "name": "Hamilton Cocktail Bar",
          "shows": 1,
          "price_min": 899,
          "price_max": 899,
          "next_date": "2026-07-18",
          "growth": 0
        },
        {
          "name": "THT Ground Floor Bar 23",
          "shows": 1,
          "price_min": null,
          "price_max": null,
          "next_date": "2026-07-23",
          "growth": 0
        },
        {
          "name": "THT Ground Floor Bar 30",
          "shows": 1,
          "price_min": null,
          "price_max": null,
          "next_date": "2026-07-30",
          "growth": 0
        },
        {
          "name": "Bighorn Arena",
          "shows": 1,
          "price_min": 2999,
          "price_max": 6499,
          "next_date": "2026-10-04",
          "growth": 0
        }
      ],
      "unlisted_shows": 33
    },
    "Delhi": {
      "total_shows": 46,
      "venues": [
        {
          "name": "Basko",
          "shows": 4,
          "price_min": 500,
          "price_max": 4000,
          "next_date": "2026-07-01",
          "growth": 1
        },
        {
          "name": "The Soho Garden",
          "shows": 2,
          "price_min": 199,
          "price_max": 199,
          "next_date": "2026-07-01",
          "growth": null
        },
        {
          "name": "Ambassador New Delhi, IHCL SeleQtions",
          "shows": 2,
          "price_min": 1799,
          "price_max": 1799,
          "next_date": "2026-07-12",
          "growth": 1
        },
        {
          "name": "Kamani Auditorium",
          "shows": 2,
          "price_min": 0,
          "price_max": 499,
          "next_date": "2026-07-12",
          "growth": 1
        },
        {
          "name": "Yashobhoomi Convention Center",
          "shows": 2,
          "price_min": 699,
          "price_max": 1999,
          "next_date": "2026-07-18",
          "growth": 1
        },
        {
          "name": "Talkatora Indoor Stadium",
          "shows": 2,
          "price_min": 799,
          "price_max": 1499,
          "next_date": "2026-08-14",
          "growth": null
        },
        {
          "name": "Dirty Good | One Golden Mile, Netaji Nagar",
          "shows": 2,
          "price_min": 699,
          "price_max": 1000,
          "next_date": "2026-07-11",
          "growth": 0
        },
        {
          "name": "Yashobhoomi",
          "shows": 2,
          "price_min": 1299,
          "price_max": 2199,
          "next_date": "2026-08-16",
          "growth": 0
        },
        {
          "name": "The Terrace",
          "shows": 1,
          "price_min": 399,
          "price_max": 399,
          "next_date": "2026-06-30",
          "growth": -2
        },
        {
          "name": "Zorba The Buddha",
          "shows": 1,
          "price_min": 1985,
          "price_max": 1985,
          "next_date": "2026-07-02",
          "growth": null
        },
        {
          "name": "Kedarnath Sahni Auditorium",
          "shows": 1,
          "price_min": 500,
          "price_max": 500,
          "next_date": "2026-07-04",
          "growth": null
        },
        {
          "name": "DLF Club 5",
          "shows": 1,
          "price_min": 999,
          "price_max": 999,
          "next_date": "2026-07-04",
          "growth": null
        },
        {
          "name": "The Laugh Casa, Rcube Monad Mall",
          "shows": 1,
          "price_min": 499,
          "price_max": 499,
          "next_date": "2026-07-04",
          "growth": 0
        },
        {
          "name": "The Laugh Store",
          "shows": 1,
          "price_min": 499,
          "price_max": 499,
          "next_date": "2026-07-05",
          "growth": 0
        },
        {
          "name": "Yashobhoomi Convention Centre-Exhibition Hall 1C",
          "shows": 1,
          "price_min": 1499,
          "price_max": 1499,
          "next_date": "2026-07-11",
          "growth": 0
        },
        {
          "name": "The Piano Man, Eldeco Centre",
          "shows": 1,
          "price_min": 1769,
          "price_max": 1769,
          "next_date": "2026-07-11",
          "growth": 0
        },
        {
          "name": "Excelsior Auditorium, Sector 43",
          "shows": 1,
          "price_min": 399,
          "price_max": 399,
          "next_date": "2026-07-11",
          "growth": 0
        },
        {
          "name": "Bira 91 Taproom",
          "shows": 1,
          "price_min": 250,
          "price_max": 250,
          "next_date": "2026-07-12",
          "growth": 0
        },
        {
          "name": "Shri Ram Centre for Performing Arts",
          "shows": 1,
          "price_min": 100,
          "price_max": 100,
          "next_date": "2026-07-16",
          "growth": -1
        },
        {
          "name": "Epicentre",
          "shows": 1,
          "price_min": 1000,
          "price_max": 1000,
          "next_date": "2026-07-19",
          "growth": null
        },
        {
          "name": "Bharat Mandapam",
          "shows": 1,
          "price_min": 885,
          "price_max": 885,
          "next_date": "2026-07-26",
          "growth": 0
        },
        {
          "name": "Aiwan-E-Ghalib Auditorium",
          "shows": 1,
          "price_min": 599,
          "price_max": 599,
          "next_date": "2026-08-01",
          "growth": 0
        },
        {
          "name": "Venue To Be Announced",
          "shows": 1,
          "price_min": 1750,
          "price_max": 1750,
          "next_date": "2026-12-19",
          "growth": 0
        },
        {
          "name": "Drums Of Heaven- Serving Since 1994",
          "shows": 1,
          "price_min": null,
          "price_max": null,
          "next_date": "2026-07-01",
          "growth": null
        },
        {
          "name": "Barish Lounge & Rooftop | Gardens Galleria Mall, Sector 38",
          "shows": 1,
          "price_min": 300,
          "price_max": 300,
          "next_date": "2026-07-01",
          "growth": null
        },
        {
          "name": "The Beer Caf\u00e9",
          "shows": 1,
          "price_min": 400,
          "price_max": 400,
          "next_date": "2026-07-04",
          "growth": null
        },
        {
          "name": "Punjabi Bagh Club",
          "shows": 1,
          "price_min": 799,
          "price_max": 799,
          "next_date": "2026-07-05",
          "growth": 0
        },
        {
          "name": "The Piano Man | Eldeco Centre",
          "shows": 1,
          "price_min": 943,
          "price_max": 943,
          "next_date": "2026-07-10",
          "growth": 0
        },
        {
          "name": "Akshara Theatre",
          "shows": 1,
          "price_min": 999,
          "price_max": 999,
          "next_date": "2026-07-11",
          "growth": null
        },
        {
          "name": "ISKCON Temple Noida",
          "shows": 1,
          "price_min": 699,
          "price_max": 699,
          "next_date": "2026-08-02",
          "growth": null
        }
      ],
      "unlisted_shows": 6
    },
    "Chennai": {
      "total_shows": 25,
      "venues": [
        {
          "name": "Multiple Venues",
          "shows": 5,
          "price_min": 349,
          "price_max": 4000,
          "next_date": "2026-07-11",
          "growth": 0
        },
        {
          "name": "Hard Rock Cafe, Nungabakkam",
          "shows": 3,
          "price_min": 249,
          "price_max": 1000,
          "next_date": "2026-07-03",
          "growth": 0
        },
        {
          "name": "Narada Gana Sabha Auditorium",
          "shows": 2,
          "price_min": 349,
          "price_max": 350,
          "next_date": "2026-07-19",
          "growth": 0
        },
        {
          "name": "Rhapsody - Courtyard by Marriott",
          "shows": 1,
          "price_min": 101,
          "price_max": 101,
          "next_date": "2026-07-01",
          "growth": 0
        },
        {
          "name": "Secret Story",
          "shows": 1,
          "price_min": 1000,
          "price_max": 1000,
          "next_date": "2026-07-05",
          "growth": 0
        },
        {
          "name": "S. A. College of Arts and Science",
          "shows": 1,
          "price_min": 499,
          "price_max": 499,
          "next_date": "2026-07-11",
          "growth": 0
        },
        {
          "name": "The Music Academy",
          "shows": 1,
          "price_min": 499,
          "price_max": 499,
          "next_date": "2026-07-26",
          "growth": 0
        },
        {
          "name": "Raja Annamalai Mandram",
          "shows": 1,
          "price_min": 300,
          "price_max": 300,
          "next_date": "2026-07-26",
          "growth": 0
        },
        {
          "name": "YMCA Nandanam",
          "shows": 1,
          "price_min": 999,
          "price_max": 999,
          "next_date": "2026-08-01",
          "growth": 0
        },
        {
          "name": "YMCA Grounds",
          "shows": 1,
          "price_min": 499,
          "price_max": 499,
          "next_date": "2026-09-05",
          "growth": 0
        },
        {
          "name": "Bengaluru LIVE,",
          "shows": 1,
          "price_min": 4000,
          "price_max": 4000,
          "next_date": "2027-01-29",
          "growth": null
        },
        {
          "name": "VGP Wonder World",
          "shows": 1,
          "price_min": 499,
          "price_max": 499,
          "next_date": "2026-07-04",
          "growth": null
        },
        {
          "name": "Hard Rock Cafe | Nungambakkam,",
          "shows": 1,
          "price_min": 249,
          "price_max": 249,
          "next_date": "2026-07-04",
          "growth": 0
        },
        {
          "name": "S. A. College of Arts & Science",
          "shows": 1,
          "price_min": 499,
          "price_max": 499,
          "next_date": "2026-07-11",
          "growth": 0
        },
        {
          "name": "165\u00b0 Hot - Adyar",
          "shows": 1,
          "price_min": 599,
          "price_max": 599,
          "next_date": "2026-07-12",
          "growth": null
        },
        {
          "name": "Victoria Public Hall",
          "shows": 1,
          "price_min": 499,
          "price_max": 499,
          "next_date": "2026-07-19",
          "growth": 0
        },
        {
          "name": "IIT Madras campus",
          "shows": 1,
          "price_min": 250,
          "price_max": 250,
          "next_date": "2026-08-02",
          "growth": 0
        }
      ],
      "unlisted_shows": 1
    },
    "Mumbai": {
      "total_shows": 52,
      "venues": [
        {
          "name": "Shanmukhananda Hall",
          "shows": 5,
          "price_min": 499,
          "price_max": 999,
          "next_date": "2026-07-12",
          "growth": -3
        },
        {
          "name": "Prabodhankar Thackeray Audi",
          "shows": 3,
          "price_min": 200,
          "price_max": 300,
          "next_date": "2026-07-18",
          "growth": 0
        },
        {
          "name": "Mahalaxmi Race Course",
          "shows": 3,
          "price_min": 3500,
          "price_max": 4000,
          "next_date": "2026-11-21",
          "growth": 0
        },
        {
          "name": "Venue to be announced",
          "shows": 3,
          "price_min": 699,
          "price_max": 5000,
          "next_date": "2026-09-13",
          "growth": 2
        },
        {
          "name": "Four Seasons Hotel, Worli",
          "shows": 2,
          "price_min": 1299,
          "price_max": 1299,
          "next_date": "2026-07-05",
          "growth": null
        },
        {
          "name": "The Studio Theatre, NMACC",
          "shows": 2,
          "price_min": 750,
          "price_max": 1599,
          "next_date": "2026-07-16",
          "growth": null
        },
        {
          "name": "The Grand Theatre, NMACC",
          "shows": 2,
          "price_min": 1499,
          "price_max": 2500,
          "next_date": "2026-07-18",
          "growth": 0
        },
        {
          "name": "Jazz@38 by Asilo",
          "shows": 1,
          "price_min": 500,
          "price_max": 500,
          "next_date": "2026-07-02",
          "growth": null
        },
        {
          "name": "Hitchki, Bandra East",
          "shows": 1,
          "price_min": 299,
          "price_max": 299,
          "next_date": "2026-07-04",
          "growth": null
        },
        {
          "name": "The Fine Arts Society",
          "shows": 1,
          "price_min": 799,
          "price_max": 799,
          "next_date": "2026-07-04",
          "growth": 0
        },
        {
          "name": "Hotel Satkar Grande",
          "shows": 1,
          "price_min": 600,
          "price_max": 600,
          "next_date": "2026-07-04",
          "growth": null
        },
        {
          "name": "Antisocial - Lower Parel",
          "shows": 1,
          "price_min": 2065,
          "price_max": 2065,
          "next_date": "2026-07-09",
          "growth": null
        },
        {
          "name": "Vishnudas Bhave Natyagruha",
          "shows": 1,
          "price_min": 300,
          "price_max": 300,
          "next_date": "2026-07-10",
          "growth": 0
        },
        {
          "name": "Jasmine Hall, Jio World Convention Centre",
          "shows": 1,
          "price_min": 1470,
          "price_max": 1470,
          "next_date": "2026-07-18",
          "growth": null
        },
        {
          "name": "Royal Opera House Theatre",
          "shows": 1,
          "price_min": 899,
          "price_max": 899,
          "next_date": "2026-07-18",
          "growth": null
        },
        {
          "name": "Dinanath Mangeshkar Natyagruha",
          "shows": 1,
          "price_min": 300,
          "price_max": 300,
          "next_date": "2026-07-18",
          "growth": 0
        },
        {
          "name": "Yashwant Natya Mandir",
          "shows": 1,
          "price_min": 200,
          "price_max": 200,
          "next_date": "2026-07-22",
          "growth": 0
        },
        {
          "name": "Regal Room, Trident Hotel",
          "shows": 1,
          "price_min": 11800,
          "price_max": 11800,
          "next_date": "2026-07-24",
          "growth": null
        },
        {
          "name": "Ravindra Natya Mandir",
          "shows": 1,
          "price_min": 100,
          "price_max": 100,
          "next_date": "2026-07-26",
          "growth": 0
        },
        {
          "name": "DOME, SVP Stadium",
          "shows": 1,
          "price_min": 2199,
          "price_max": 2199,
          "next_date": "2026-08-01",
          "growth": null
        },
        {
          "name": "Rangasharda Auditorium",
          "shows": 1,
          "price_min": 499,
          "price_max": 499,
          "next_date": "2026-08-08",
          "growth": null
        },
        {
          "name": "Opa! Bar & Cafe - Peninsula Grand Hotel",
          "shows": 1,
          "price_min": 1000,
          "price_max": 1000,
          "next_date": "2026-06-30",
          "growth": null
        },
        {
          "name": "Lyla | Bandra Kurla Complex,",
          "shows": 1,
          "price_min": 200,
          "price_max": 200,
          "next_date": "2026-07-01",
          "growth": 0
        },
        {
          "name": "Jio World Convention Centre",
          "shows": 1,
          "price_min": 499,
          "price_max": 499,
          "next_date": "2026-07-04",
          "growth": 0
        },
        {
          "name": "BKC DIVE.",
          "shows": 1,
          "price_min": 299,
          "price_max": 299,
          "next_date": "2026-07-04",
          "growth": null
        },
        {
          "name": "The Game Palacio",
          "shows": 1,
          "price_min": 249,
          "price_max": 249,
          "next_date": "2026-07-04",
          "growth": 0
        },
        {
          "name": "Carnival By Tr\u00e8sind | Santacruz West,",
          "shows": 1,
          "price_min": 250,
          "price_max": 250,
          "next_date": "2026-07-04",
          "growth": null
        },
        {
          "name": "Third Bell Studios",
          "shows": 1,
          "price_min": 599,
          "price_max": 599,
          "next_date": "2026-07-10",
          "growth": 0
        },
        {
          "name": "antiSOCIAL, Lower Parel",
          "shows": 1,
          "price_min": 800,
          "price_max": 800,
          "next_date": "2026-07-18",
          "growth": null
        },
        {
          "name": "Jio World Garden",
          "shows": 1,
          "price_min": 5000,
          "price_max": 5000,
          "next_date": "2027-01-27",
          "growth": 0
        },
        {
          "name": "Khar SOCIAL",
          "shows": 1,
          "price_min": null,
          "price_max": null,
          "next_date": "2026-07-03",
          "growth": 0
        },
        {
          "name": "10 PM ONW",
          "shows": 1,
          "price_min": 1999,
          "price_max": 7200,
          "next_date": "2026-07-10",
          "growth": null
        },
        {
          "name": "Empower",
          "shows": 1,
          "price_min": 1500,
          "price_max": 4000,
          "next_date": "2026-08-08",
          "growth": null
        }
      ],
      "unlisted_shows": 6
    },
    "Goa": {
      "total_shows": 20,
      "venues": [
        {
          "name": "Uncultured | Assagao,",
          "shows": 2,
          "price_min": 500,
          "price_max": 500,
          "next_date": "2026-07-01",
          "growth": 0
        },
        {
          "name": "Hammerzz Makarena",
          "shows": 1,
          "price_min": 1000,
          "price_max": 1000,
          "next_date": "2026-07-03",
          "growth": null
        },
        {
          "name": "Orion Beach Club",
          "shows": 1,
          "price_min": 1200,
          "price_max": 1200,
          "next_date": "2026-07-03",
          "growth": 0
        },
        {
          "name": "Kala Academy",
          "shows": 1,
          "price_min": 300,
          "price_max": 300,
          "next_date": "2026-07-04",
          "growth": 0
        },
        {
          "name": "HOUSE OF CHAPORA",
          "shows": 1,
          "price_min": 1100,
          "price_max": 1100,
          "next_date": "2026-07-05",
          "growth": -1
        },
        {
          "name": "Dynamo",
          "shows": 1,
          "price_min": 999,
          "price_max": 999,
          "next_date": "2026-07-11",
          "growth": 0
        },
        {
          "name": "Calangute",
          "shows": 1,
          "price_min": 179000,
          "price_max": 179000,
          "next_date": "2026-07-16",
          "growth": 0
        },
        {
          "name": "Venue To Be Announced",
          "shows": 1,
          "price_min": 499,
          "price_max": 499,
          "next_date": "2026-08-15",
          "growth": 0
        },
        {
          "name": "Vagator",
          "shows": 1,
          "price_min": 2999,
          "price_max": 2999,
          "next_date": "2026-12-31",
          "growth": 0
        },
        {
          "name": "House of Chapora",
          "shows": 1,
          "price_min": 1000,
          "price_max": 1000,
          "next_date": "2026-06-30",
          "growth": 0
        },
        {
          "name": "Orion Beach Restaurant",
          "shows": 1,
          "price_min": 1200,
          "price_max": 1200,
          "next_date": "2026-07-03",
          "growth": 0
        },
        {
          "name": "Raeeth | Vagator,",
          "shows": 1,
          "price_min": 1190,
          "price_max": 1190,
          "next_date": "2026-07-03",
          "growth": 0
        },
        {
          "name": "Fiturr",
          "shows": 1,
          "price_min": 999,
          "price_max": 999,
          "next_date": "2026-07-04",
          "growth": 0
        },
        {
          "name": "Nines by The Evren",
          "shows": 1,
          "price_min": 1000,
          "price_max": 1000,
          "next_date": "2026-07-04",
          "growth": null
        },
        {
          "name": "salud",
          "shows": 1,
          "price_min": 1499,
          "price_max": 1499,
          "next_date": "2026-08-14",
          "growth": 0
        },
        {
          "name": "Empower",
          "shows": 1,
          "price_min": 1500,
          "price_max": 3000,
          "next_date": "2026-08-14",
          "growth": 0
        },
        {
          "name": "The Decade Ritual",
          "shows": 1,
          "price_min": 1999,
          "price_max": 3500,
          "next_date": "31 Decembe",
          "growth": 0
        }
      ],
      "unlisted_shows": 2
    },
    "NCPA.": {
      "total_shows": 1,
      "venues": [
        {
          "name": "Jamshed Bhabha Theatre",
          "shows": 1,
          "price_min": 400,
          "price_max": 400,
          "next_date": "2026-07-03",
          "growth": null
        }
      ],
      "unlisted_shows": 0
    },
    "Pune": {
      "total_shows": 35,
      "venues": [
        {
          "name": "MahaLaxmi Lawns",
          "shows": 3,
          "price_min": 399,
          "price_max": 999,
          "next_date": "2026-07-04",
          "growth": 0
        },
        {
          "name": "Bira 91 Taproom, The Mills",
          "shows": 2,
          "price_min": 120,
          "price_max": 250,
          "next_date": "2026-07-04",
          "growth": 0
        },
        {
          "name": "The High Spirits Cafe",
          "shows": 2,
          "price_min": 499,
          "price_max": 999,
          "next_date": "2026-07-05",
          "growth": 1
        },
        {
          "name": "Venue To Be Announced",
          "shows": 2,
          "price_min": 399,
          "price_max": 500,
          "next_date": "2026-07-18",
          "growth": 1
        },
        {
          "name": "Yashwantrao Chavan Natyagruha",
          "shows": 2,
          "price_min": 200,
          "price_max": 300,
          "next_date": "2026-07-18",
          "growth": 1
        },
        {
          "name": "Phoenix Marketcity",
          "shows": 2,
          "price_min": 499,
          "price_max": 999,
          "next_date": "2026-09-06",
          "growth": 0
        },
        {
          "name": "Ballr",
          "shows": 1,
          "price_min": 1000,
          "price_max": 1000,
          "next_date": "2026-07-05",
          "growth": null
        },
        {
          "name": "Vithal Tupe Sabhagruh",
          "shows": 1,
          "price_min": 200,
          "price_max": 200,
          "next_date": "2026-07-11",
          "growth": 0
        },
        {
          "name": "Ganesh Kala Krida Manch",
          "shows": 1,
          "price_min": 300,
          "price_max": 300,
          "next_date": "2026-07-11",
          "growth": 0
        },
        {
          "name": "Ram Krishna More Auditorium",
          "shows": 1,
          "price_min": 300,
          "price_max": 300,
          "next_date": "2026-07-17",
          "growth": 0
        },
        {
          "name": "Pandit Farms",
          "shows": 1,
          "price_min": 500,
          "price_max": 500,
          "next_date": "2026-07-25",
          "growth": 0
        },
        {
          "name": "Bal Gandharva Rang Mandir",
          "shows": 1,
          "price_min": 299,
          "price_max": 299,
          "next_date": "2026-07-26",
          "growth": null
        },
        {
          "name": "Liberty Square, Phoenix Marketcity",
          "shows": 1,
          "price_min": 499,
          "price_max": 499,
          "next_date": "2026-09-12",
          "growth": 0
        },
        {
          "name": "Liberty Square Phoenix Mall, Viman Nagar",
          "shows": 1,
          "price_min": 499,
          "price_max": 499,
          "next_date": "2026-09-27",
          "growth": null
        },
        {
          "name": "Liberty Square, Phoenix Avenue of Stars",
          "shows": 1,
          "price_min": 999,
          "price_max": 999,
          "next_date": "2026-10-25",
          "growth": 0
        },
        {
          "name": "Phoenix Market City",
          "shows": 1,
          "price_min": 799,
          "price_max": 799,
          "next_date": "2026-11-21",
          "growth": 0
        },
        {
          "name": "Favela | Hinjawadi,",
          "shows": 1,
          "price_min": 999,
          "price_max": 999,
          "next_date": "2026-07-02",
          "growth": null
        },
        {
          "name": "The Daily All Day | Koregaon Park,",
          "shows": 1,
          "price_min": 500,
          "price_max": 500,
          "next_date": "2026-07-03",
          "growth": null
        },
        {
          "name": "FC Road Social",
          "shows": 1,
          "price_min": 299,
          "price_max": 299,
          "next_date": "2026-07-04",
          "growth": 0
        },
        {
          "name": "The Game Super Park",
          "shows": 1,
          "price_min": 249,
          "price_max": 249,
          "next_date": "2026-07-04",
          "growth": 0
        },
        {
          "name": "Epitome | The Mills, Bund Garden Road",
          "shows": 1,
          "price_min": 599,
          "price_max": 599,
          "next_date": "2026-07-05",
          "growth": null
        },
        {
          "name": "High Spirits | Mundhwa,",
          "shows": 1,
          "price_min": 200,
          "price_max": 200,
          "next_date": "2026-07-11",
          "growth": 0
        },
        {
          "name": "antiSOCIAL",
          "shows": 1,
          "price_min": 799,
          "price_max": 799,
          "next_date": "2026-07-12",
          "growth": null
        },
        {
          "name": "Chhatrapati Shahu Maharaj Research, Training and Human Development Institute (SARTHI), Headquarters",
          "shows": 1,
          "price_min": null,
          "price_max": null,
          "next_date": "2026-07-26",
          "growth": null
        },
        {
          "name": "Sneaker Led Cultural Fest",
          "shows": 1,
          "price_min": 999,
          "price_max": 3499,
          "next_date": "2026-07-05",
          "growth": 0
        }
      ],
      "unlisted_shows": 3
    },
    "Puducherry": {
      "total_shows": 1,
      "venues": [
        {
          "name": "Expo Ground",
          "shows": 1,
          "price_min": 499,
          "price_max": 499,
          "next_date": "2026-07-04",
          "growth": 0
        }
      ],
      "unlisted_shows": 0
    },
    "Koramangala": {
      "total_shows": 1,
      "venues": [
        {
          "name": "Prabhath Kaladwaraka Auditorium",
          "shows": 1,
          "price_min": 1499,
          "price_max": 1499,
          "next_date": "2026-07-11",
          "growth": null
        }
      ],
      "unlisted_shows": 0
    },
    "Whitefield, Bengaluru": {
      "total_shows": 1,
      "venues": [
        {
          "name": "MLR Convention Centre",
          "shows": 1,
          "price_min": 1432,
          "price_max": 1432,
          "next_date": "2026-07-11",
          "growth": null
        }
      ],
      "unlisted_shows": 0
    },
    "Thane (W)": {
      "total_shows": 1,
      "venues": [
        {
          "name": "Kashinath Ghanekar Natyagruha",
          "shows": 1,
          "price_min": 499,
          "price_max": 499,
          "next_date": "2026-07-31",
          "growth": null
        }
      ],
      "unlisted_shows": 0
    },
    "Guwahati": {
      "total_shows": 2,
      "venues": [
        {
          "name": "Khanapara Veterinary Ground",
          "shows": 1,
          "price_min": 5000,
          "price_max": 5000,
          "next_date": "2026-11-17",
          "growth": 0
        },
        {
          "name": "Berserk Entertainment",
          "shows": 1,
          "price_min": 699,
          "price_max": 1299,
          "next_date": "2026-07-10",
          "growth": 0
        }
      ],
      "unlisted_shows": 0
    },
    "Hyderabad": {
      "total_shows": 20,
      "venues": [
        {
          "name": "EXT | Film Nagar,",
          "shows": 1,
          "price_min": 999,
          "price_max": 999,
          "next_date": "2026-07-03",
          "growth": 0
        },
        {
          "name": "Quake Arena",
          "shows": 1,
          "price_min": 199,
          "price_max": 199,
          "next_date": "2026-07-03",
          "growth": null
        },
        {
          "name": "Quake | Kondapur,",
          "shows": 1,
          "price_min": 799,
          "price_max": 799,
          "next_date": "2026-07-04",
          "growth": 0
        },
        {
          "name": "The Game Palacio",
          "shows": 1,
          "price_min": 250,
          "price_max": 250,
          "next_date": "2026-07-04",
          "growth": null
        },
        {
          "name": "Mindspace Social | Hitech City,",
          "shows": 1,
          "price_min": 299,
          "price_max": 299,
          "next_date": "2026-07-04",
          "growth": 0
        },
        {
          "name": "Haze Kitchen & Bar  | Gachibowli,",
          "shows": 1,
          "price_min": 299,
          "price_max": 299,
          "next_date": "2026-07-04",
          "growth": null
        },
        {
          "name": "Tavaro Resorts and Events",
          "shows": 1,
          "price_min": 499,
          "price_max": 499,
          "next_date": "2026-07-04",
          "growth": -2
        },
        {
          "name": "Ameyaa Social",
          "shows": 1,
          "price_min": 599,
          "price_max": 599,
          "next_date": "2026-07-11",
          "growth": 0
        },
        {
          "name": "Shilpakala vedika",
          "shows": 1,
          "price_min": 1500,
          "price_max": 1500,
          "next_date": "2026-07-31",
          "growth": 0
        },
        {
          "name": "S S Convention Centre",
          "shows": 1,
          "price_min": 2099,
          "price_max": 2099,
          "next_date": "2026-09-20",
          "growth": 0
        },
        {
          "name": "Venue to be announced",
          "shows": 1,
          "price_min": 999,
          "price_max": 999,
          "next_date": "2026-11-28",
          "growth": 0
        },
        {
          "name": "Empower",
          "shows": 1,
          "price_min": 1000,
          "price_max": 2000,
          "next_date": "2026-08-16",
          "growth": 0
        }
      ],
      "unlisted_shows": 8
    },
    "Kolkata": {
      "total_shows": 9,
      "venues": [
        {
          "name": "Lucky Tigerr",
          "shows": 1,
          "price_min": 0,
          "price_max": 0,
          "next_date": "2026-07-04",
          "growth": null
        },
        {
          "name": "Scrapyard | Camac Street Area,",
          "shows": 1,
          "price_min": 299,
          "price_max": 299,
          "next_date": "2026-07-05",
          "growth": 0
        },
        {
          "name": "Mahanayak Uttam Manch",
          "shows": 1,
          "price_min": 300,
          "price_max": 300,
          "next_date": "2026-07-11",
          "growth": 0
        },
        {
          "name": "Venue to be announced",
          "shows": 1,
          "price_min": 999,
          "price_max": 999,
          "next_date": "2026-07-25",
          "growth": 0
        },
        {
          "name": "Kolkata Centre for Creativity",
          "shows": 1,
          "price_min": 1499,
          "price_max": 1499,
          "next_date": "2026-07-31",
          "growth": 0
        },
        {
          "name": "Jai Hind Auditorium",
          "shows": 1,
          "price_min": 399,
          "price_max": 399,
          "next_date": "2026-08-08",
          "growth": 0
        },
        {
          "name": "Mahajati Sadan Auditorium",
          "shows": 1,
          "price_min": 400,
          "price_max": 400,
          "next_date": "2026-08-22",
          "growth": 0
        },
        {
          "name": "Barrackpore Sukanta Sadan",
          "shows": 1,
          "price_min": 600,
          "price_max": 600,
          "next_date": "2026-09-27",
          "growth": null
        },
        {
          "name": "Kala Mandir",
          "shows": 1,
          "price_min": 600,
          "price_max": 600,
          "next_date": "2026-12-12",
          "growth": null
        }
      ],
      "unlisted_shows": 0
    },
    "Ladakh": {
      "total_shows": 1,
      "venues": [
        {
          "name": "Chuchot Ground",
          "shows": 1,
          "price_min": 999,
          "price_max": 999,
          "next_date": "2026-09-04",
          "growth": 0
        }
      ],
      "unlisted_shows": 0
    },
    "Dubai": {
      "total_shows": 1,
      "venues": [
        {
          "name": "Dubai Parks and Resorts",
          "shows": 1,
          "price_min": 350,
          "price_max": 350,
          "next_date": "2026-11-05",
          "growth": 0
        }
      ],
      "unlisted_shows": 0
    },
    "India": {
      "total_shows": 1,
      "venues": [
        {
          "name": "Venue to be announced",
          "shows": 1,
          "price_min": null,
          "price_max": null,
          "next_date": null,
          "growth": 0
        }
      ],
      "unlisted_shows": 0
    },
    "Gangtok": {
      "total_shows": 1,
      "venues": [],
      "unlisted_shows": 1
    },
    "Jaipur": {
      "total_shows": 1,
      "venues": [],
      "unlisted_shows": 1
    },
    "Mysore": {
      "total_shows": 1,
      "venues": [],
      "unlisted_shows": 1
    },
    "Kochi": {
      "total_shows": 2,
      "venues": [],
      "unlisted_shows": 2
    },
    "Ahmedabad": {
      "total_shows": 1,
      "venues": [
        {
          "name": "Empower",
          "shows": 1,
          "price_min": 1500,
          "price_max": 3000,
          "next_date": "2026-08-15",
          "growth": 0
        }
      ],
      "unlisted_shows": 0
    }
  }
}